{
  "source": "<project-root>\\gameplay-tables-decompiled\\Assetbundles\\ab_script_cutscene\\luac\\LIFETIME_END_NKM_UNIT_C_ALT_SEO_YOON_SPRING.lua",
  "rootName": "m_dicNKCCutScenTempletByID",
  "recordCount": 3,
  "records": [
    {
      "m_CutScenProcessKey": 1,
      "m_CutScenID": 10040502,
      "m_CutScenStrID": "LIFETIME_END_NKM_UNIT_C_ALT_SEO_YOON_SPRING",
      "m_bWaitClick": false,
      "m_fWaitTime": 0,
      "m_BGFileName": "LIFETIME",
      "m_StartBGMFileName": "CUTSCENE_HOPE"
    },
    {
      "m_CutScenKey_Talk": "LIFETIME_END_NKM_UNIT_C_ALT_SEO_YOON_SPRING@2#Talk",
      "m_CutScenProcessKey": 2,
      "m_CutScenID": 10040502,
      "m_CutScenStrID": "LIFETIME_END_NKM_UNIT_C_ALT_SEO_YOON_SPRING",
      "m_bWaitClick": true,
      "m_fWaitTime": 0,
      "m_Face": "UNIT_LAUGH",
      "m_CharStrID": "SEO_YOON_ALT_SPRING_NULL",
      "m_Pos": "C",
      "m_Talk_KOREA": "x\u000e8gp \u000184 \u000b9t wd\f8\n8gnv\u000180 ^n i\\w\n8w`...... \f9\r8n\u000188qncZ p^ }\u000191h\u000180 s\u000188Z\u000184l\f8. p\n8cZ Xz\r8u\u000b9joZ }\u000191oZ [`\u000b9^\u000185`l\f8.",
      "m_fTalkTime": 0.03,
      "m_Talk_JPN": "\n9k\n9\u000185\n9vXf\n9\u000b8\u000e9\n9kX\u000b9\n9g\n9\u000e8\n9}\n9w\n9a\n9\u000190\n9mXg\n9`\n8v\n8v\n9gX`\n9\u000b9X_XXw\n9\n9|\n9g\n9\u000e8Xf\u00128\u000191q\n9j\n9v\n9c\n9p\n9\f9\n9Z\n8Xw\n9XXt\u000190\f9\u000183Xf\u00128\u000191q\n9j\n9\u000190\n9k\n9\u000b9X_\n8X",
      "m_Talk_ENG": "I can't tell you everything, but please keep your faith in me. I'll do the same.",
      "m_Talk_TWN": "mhZ\u000182\u000f8f\u000190v\u000f9\f9\u00129e\u000b8\u000e8\u000180X\u000e8_\n8n_lZ\u00128\u000186\u000b9Y[\n8v\n8v\u00128\u000189\\\u00128\u000187u\u00129\u000190`\u00128\u000185\r9y\u000b9m\u000184\u00128\u000191q^e\u00129dw\u00139\u000188`^e\u00128\u000185\r9nYm\u000184\u00128\u000191q\n8\n9i\\lZ\n8X",
      "m_Talk_THA": "\u000184_\u000184\u000184k\u000184Z\u000184]\u000185\n8\u000184u\u000185^\u000184\u000f8\u000184i\u000184\u000184\u000184\n9\u000184{\u000184r\u000185^\u000184\u000f8\u000184]\u000185Y\u000184y\u000185_\u000184Z\u000184\u000184\u000184g\u000184\r9\u000184\u000184]\u000185Z\u000184q\u000185^\u000185Z\u000184\f8\u000185_ \u000185\n9\u000184\f9\u000185^\u000185X\u000184m\u000184s\u000184\f8\u000185\n8\u000184\u000b8\u000184\u000183\u000185^\u000184{\u000184q\u000184\u000185^\u000184k\u000185Y\u000184k\u000184\f9\u000184\u000184w\u000184_\u000184\u000184k\u000184\f8\u000185_\u000184w\u000184r\u000185\n8\u000184h\u000184{\u000184~ \u000185\n9\u000184u\u000184~\u000184_\u000184\u000184k\u000184\n9\u000185]\u000184^\u000184~\u000184\u000e8\u000184s\u000184\u000184i\u000184j\u000184\u000f8\u000185Y\u000184k\u000184\f9\u000184\u000184w\u000184Z\u000184\u000184\u000184g\u000185\n8\u000184\u000b8\u000185^\u000184k\u000184\n9\u000184\u000184k",
      "m_Talk_VTN": "T\u000195\u000180i kh\u000195\u000180ng th\u000187Y n\u000195\u000f9i v\u000187mi ng\u000195pi m\u000187ai th\u000187\u000e9, nh\u000198~ng h\u000195sy tin \u000187\r9 t\u000195\u000180i. T\u000195\u000180i c\u000197\u000e9ng s\u000186\u000189 nh\u000198~ v\u000186{y.",
      "m_Talk_SCN": "k\u000189Z\u000182\u00128\u000184aY\u000189\u00129[\u000e8Y\u000e8\u00129e\u000b8}_\u00128\u000189p\u00139\u000188`\u00128\u000189\\\u00128\u000187u\u00129db}\u000183\u00128\u000189pm\u000184\u00128\u000191q^e\n8X ^e\u00128\u000185\r9\u00128\u000188lm\u000184\u00128\u000191q\n8\n9o\u000191lZ\u00139\u000188\n9",
      "m_Talk_DEU": "Ich kann Ihnen zwar nicht alles erz\u000195thlen, aber bitte glauben Sie an mich. Ich tu das Gleiche.",
      "m_Talk_FRA": "Je ne peux pas tout vous dire, mais continuez \u000195p croire en moi, s'il vous pla\u000195|t. Je ferai de m\u000195xme."
    },
    {
      "m_CutScenProcessKey": 3,
      "m_CutScenID": 10040502,
      "m_CutScenStrID": "LIFETIME_END_NKM_UNIT_C_ALT_SEO_YOON_SPRING",
      "m_bWaitClick": false,
      "m_fWaitTime": 0,
      "m_bFadeIn": false,
      "m_fFadeTime": 3,
      "m_bFadeWhite": true
    }
  ],
  "root": [
    {
      "m_CutScenProcessKey": 1,
      "m_CutScenID": 10040502,
      "m_CutScenStrID": "LIFETIME_END_NKM_UNIT_C_ALT_SEO_YOON_SPRING",
      "m_bWaitClick": false,
      "m_fWaitTime": 0,
      "m_BGFileName": "LIFETIME",
      "m_StartBGMFileName": "CUTSCENE_HOPE"
    },
    {
      "m_CutScenKey_Talk": "LIFETIME_END_NKM_UNIT_C_ALT_SEO_YOON_SPRING@2#Talk",
      "m_CutScenProcessKey": 2,
      "m_CutScenID": 10040502,
      "m_CutScenStrID": "LIFETIME_END_NKM_UNIT_C_ALT_SEO_YOON_SPRING",
      "m_bWaitClick": true,
      "m_fWaitTime": 0,
      "m_Face": "UNIT_LAUGH",
      "m_CharStrID": "SEO_YOON_ALT_SPRING_NULL",
      "m_Pos": "C",
      "m_Talk_KOREA": "x\u000e8gp \u000184 \u000b9t wd\f8\n8gnv\u000180 ^n i\\w\n8w`...... \f9\r8n\u000188qncZ p^ }\u000191h\u000180 s\u000188Z\u000184l\f8. p\n8cZ Xz\r8u\u000b9joZ }\u000191oZ [`\u000b9^\u000185`l\f8.",
      "m_fTalkTime": 0.03,
      "m_Talk_JPN": "\n9k\n9\u000185\n9vXf\n9\u000b8\u000e9\n9kX\u000b9\n9g\n9\u000e8\n9}\n9w\n9a\n9\u000190\n9mXg\n9`\n8v\n8v\n9gX`\n9\u000b9X_XXw\n9\n9|\n9g\n9\u000e8Xf\u00128\u000191q\n9j\n9v\n9c\n9p\n9\f9\n9Z\n8Xw\n9XXt\u000190\f9\u000183Xf\u00128\u000191q\n9j\n9\u000190\n9k\n9\u000b9X_\n8X",
      "m_Talk_ENG": "I can't tell you everything, but please keep your faith in me. I'll do the same.",
      "m_Talk_TWN": "mhZ\u000182\u000f8f\u000190v\u000f9\f9\u00129e\u000b8\u000e8\u000180X\u000e8_\n8n_lZ\u00128\u000186\u000b9Y[\n8v\n8v\u00128\u000189\\\u00128\u000187u\u00129\u000190`\u00128\u000185\r9y\u000b9m\u000184\u00128\u000191q^e\u00129dw\u00139\u000188`^e\u00128\u000185\r9nYm\u000184\u00128\u000191q\n8\n9i\\lZ\n8X",
      "m_Talk_THA": "\u000184_\u000184\u000184k\u000184Z\u000184]\u000185\n8\u000184u\u000185^\u000184\u000f8\u000184i\u000184\u000184\u000184\n9\u000184{\u000184r\u000185^\u000184\u000f8\u000184]\u000185Y\u000184y\u000185_\u000184Z\u000184\u000184\u000184g\u000184\r9\u000184\u000184]\u000185Z\u000184q\u000185^\u000185Z\u000184\f8\u000185_ \u000185\n9\u000184\f9\u000185^\u000185X\u000184m\u000184s\u000184\f8\u000185\n8\u000184\u000b8\u000184\u000183\u000185^\u000184{\u000184q\u000184\u000185^\u000184k\u000185Y\u000184k\u000184\f9\u000184\u000184w\u000184_\u000184\u000184k\u000184\f8\u000185_\u000184w\u000184r\u000185\n8\u000184h\u000184{\u000184~ \u000185\n9\u000184u\u000184~\u000184_\u000184\u000184k\u000184\n9\u000185]\u000184^\u000184~\u000184\u000e8\u000184s\u000184\u000184i\u000184j\u000184\u000f8\u000185Y\u000184k\u000184\f9\u000184\u000184w\u000184Z\u000184\u000184\u000184g\u000185\n8\u000184\u000b8\u000185^\u000184k\u000184\n9\u000184\u000184k",
      "m_Talk_VTN": "T\u000195\u000180i kh\u000195\u000180ng th\u000187Y n\u000195\u000f9i v\u000187mi ng\u000195pi m\u000187ai th\u000187\u000e9, nh\u000198~ng h\u000195sy tin \u000187\r9 t\u000195\u000180i. T\u000195\u000180i c\u000197\u000e9ng s\u000186\u000189 nh\u000198~ v\u000186{y.",
      "m_Talk_SCN": "k\u000189Z\u000182\u00128\u000184aY\u000189\u00129[\u000e8Y\u000e8\u00129e\u000b8}_\u00128\u000189p\u00139\u000188`\u00128\u000189\\\u00128\u000187u\u00129db}\u000183\u00128\u000189pm\u000184\u00128\u000191q^e\n8X ^e\u00128\u000185\r9\u00128\u000188lm\u000184\u00128\u000191q\n8\n9o\u000191lZ\u00139\u000188\n9",
      "m_Talk_DEU": "Ich kann Ihnen zwar nicht alles erz\u000195thlen, aber bitte glauben Sie an mich. Ich tu das Gleiche.",
      "m_Talk_FRA": "Je ne peux pas tout vous dire, mais continuez \u000195p croire en moi, s'il vous pla\u000195|t. Je ferai de m\u000195xme."
    },
    {
      "m_CutScenProcessKey": 3,
      "m_CutScenID": 10040502,
      "m_CutScenStrID": "LIFETIME_END_NKM_UNIT_C_ALT_SEO_YOON_SPRING",
      "m_bWaitClick": false,
      "m_fWaitTime": 0,
      "m_bFadeIn": false,
      "m_fFadeTime": 3,
      "m_bFadeWhite": true
    }
  ],
  "unsupportedCount": 0,
  "unsupported": []
}