{
  "source": "<project-root>\\gameplay-tables-decompiled\\Assetbundles\\ab_script_cutscene\\luac\\LIFETIME_START_NKM_UNIT_C_FREEDOM_AKI.lua",
  "rootName": "m_dicNKCCutScenTempletByID",
  "recordCount": 60,
  "records": [
    {
      "m_CutScenID": 10500001,
      "m_CutScenStrID": "LIFETIME_START_NKM_UNIT_C_FREEDOM_AKI",
      "m_bWaitClick": false,
      "m_fWaitTime": 0,
      "m_BGFileName": "BLACK",
      "m_bFadeIn": true,
      "m_fFadeTime": 1.5,
      "m_StartBGMFileName": "CUTSCENE_SILENCE"
    },
    {
      "m_CutScenID": 10500001,
      "m_CutScenStrID": "LIFETIME_START_NKM_UNIT_C_FREEDOM_AKI",
      "m_bWaitClick": false,
      "m_fWaitTime": 0.4,
      "m_fFlashBangTime": 0.25,
      "m_StartFXSoundName": "FX_CUTSCEN_KNOCK_WOOD"
    },
    {
      "m_CutScenID": 10500001,
      "m_CutScenStrID": "LIFETIME_START_NKM_UNIT_C_FREEDOM_AKI",
      "m_bWaitClick": false,
      "m_fWaitTime": 0.4,
      "m_fFlashBangTime": 0.25
    },
    {
      "m_CutScenID": 10500001,
      "m_CutScenStrID": "LIFETIME_START_NKM_UNIT_C_FREEDOM_AKI",
      "m_bWaitClick": false,
      "m_fWaitTime": 1.5,
      "m_fFlashBangTime": 0.25
    },
    {
      "m_CutScenID": 10500001,
      "m_CutScenStrID": "LIFETIME_START_NKM_UNIT_C_FREEDOM_AKI",
      "m_bWaitClick": true,
      "m_fWaitTime": 0,
      "m_Face": "UNIT_LAUGH",
      "m_CharStrID": "AKI_FREEDOM_NULL_NULL",
      "m_Pos": "C",
      "m_Crash": 30,
      "m_Talk_KOREA": "ÂžXzÂž\r8uÂť\u000b9j~ ÂžXz~ Âž\r8u~ Âť\u000b9j~",
      "m_fTalkTime": 0.03,
      "m_Talk_USA": "ÂžXzÂž\r8uÂť\u000b9j~ ÂžXz~ Âž\r8u~ Âť\u000b9j~",
      "m_Talk_JAPAN": "ÂžXzÂž\r8uÂť\u000b9j~ ÂžXz~ Âž\r8u~ Âť\u000b9j~"
    },
    {
      "m_CutScenID": 10500001,
      "m_CutScenStrID": "LIFETIME_START_NKM_UNIT_C_FREEDOM_AKI",
      "m_bWaitClick": true,
      "m_fWaitTime": 0,
      "m_Face": "UNIT_DESPAIR",
      "m_CharStrID": "AKI_FREEDOM_NULL_NULL",
      "m_Pos": "C",
      "m_Talk_KOREA": "Âžl~Âžn\u000188...... ÂžXzÂť\r8`ÂžoZ Âť\u000182^Âť\r9z Âť\\gÂś\u000f9p Âžh\u000180Âť\f8\f8 Âś~\n8Âž\u000b9p Âś~Âť\r8`, ÂžwZÂžwn......",
      "m_fTalkTime": 0.03,
      "m_Talk_USA": "Âžl~Âžn\u000188...... ÂžXzÂť\r8`ÂžoZ Âť\u000182^Âť\r9z Âť\\gÂś\u000f9p Âžh\u000180Âť\f8\f8 Âś~\n8Âž\u000b9p Âś~Âť\r8`, ÂžwZÂžwn......",
      "m_Talk_JAPAN": "Âžl~Âžn\u000188...... ÂžXzÂť\r8`ÂžoZ Âť\u000182^Âť\r9z Âť\\gÂś\u000f9p Âžh\u000180Âť\f8\f8 Âś~\n8Âž\u000b9p Âś~Âť\r8`, ÂžwZÂžwn......"
    },
    {
      "m_CutScenID": 10500001,
      "m_CutScenStrID": "LIFETIME_START_NKM_UNIT_C_FREEDOM_AKI",
      "m_bWaitClick": true,
      "m_fWaitTime": 0,
      "m_Face": "UNIT_SURPRISE",
      "m_CharStrID": "AKI_FREEDOM_NULL_NULL",
      "m_Pos": "C",
      "m_Talk_KOREA": "Âž\f9i, Âťz\u000184Âžo\u000180 Âži\u000180Âťpt Âž\r8^Âži^ÂťZt?",
      "m_fTalkTime": 0.03,
      "m_Talk_USA": "Âž\f9i, Âťz\u000184Âžo\u000180 Âži\u000180Âťpt Âž\r8^Âži^ÂťZt?",
      "m_Talk_JAPAN": "Âž\f9i, Âťz\u000184Âžo\u000180 Âži\u000180Âťpt Âž\r8^Âži^ÂťZt?"
    },
    {
      "m_CutScenID": 10500001,
      "m_CutScenStrID": "LIFETIME_START_NKM_UNIT_C_FREEDOM_AKI",
      "m_bWaitClick": true,
      "m_fWaitTime": 0,
      "m_Face": "UNIT_PRIDE",
      "m_CharStrID": "AKI_FREEDOM_NULL_NULL",
      "m_Pos": "C",
      "m_Talk_KOREA": "Âžp\f9Âťwd, Âť\\aÂť\f9qÂžo\u000180Âť\u000b8\f8 Âž\r8j Âž\u000185jÂž\u000b9nÂť\u000e9\u000180ÂžZn Âžo\u000180Âť\r9~ Âś\u000181zÂžZoÂžo\n8 Âźi^Âž^pÂź\f9jÂť\u000b9tÂť\u000b9^Âś\u000185`Âžl\f8.",
      "m_fTalkTime": 0.03,
      "m_Talk_USA": "Âžp\f9Âťwd, Âť\\aÂť\f9qÂžo\u000180Âť\u000b8\f8 Âž\r8j Âž\u000185jÂž\u000b9nÂť\u000e9\u000180ÂžZn Âžo\u000180Âť\r9~ Âś\u000181zÂžZoÂžo\n8 Âźi^Âž^pÂź\f9jÂť\u000b9tÂť\u000b9^Âś\u000185`Âžl\f8.",
      "m_Talk_JAPAN": "Âžp\f9Âťwd, Âť\\aÂť\f9qÂžo\u000180Âť\u000b8\f8 Âž\r8j Âž\u000185jÂž\u000b9nÂť\u000e9\u000180ÂžZn Âžo\u000180Âť\r9~ Âś\u000181zÂžZoÂžo\n8 Âźi^Âž^pÂź\f9jÂť\u000b9tÂť\u000b9^Âś\u000185`Âžl\f8."
    },
    {
      "m_CutScenID": 10500001,
      "m_CutScenStrID": "LIFETIME_START_NKM_UNIT_C_FREEDOM_AKI",
      "m_bWaitClick": true,
      "m_fWaitTime": 0,
      "m_CharStrID": "AKI_FREEDOM_NULL_NULL",
      "m_Pos": "C",
      "m_Talk_KOREA": "Âžo\u000180Âť\f8~ Âť\u000f9\u000180Âť\u000e9\u000180 Âť\f8~Âť\n9\f8Âź\f9jÂś\u000f8` Âź\f9nÂťw^Âť\f8\f8 Âź\f9\u000180 ÂťgnÂťptÂž\f9\u000188Âś\u000f8pÂžh\u000180Âžl\f8.",
      "m_fTalkTime": 0.03,
      "m_Talk_USA": "Âžo\u000180Âť\f8~ Âť\u000f9\u000180Âť\u000e9\u000180 Âť\f8~Âť\n9\f8Âź\f9jÂś\u000f8` Âź\f9nÂťw^Âť\f8\f8 Âź\f9\u000180 ÂťgnÂťptÂž\f9\u000188Âś\u000f8pÂžh\u000180Âžl\f8.",
      "m_Talk_JAPAN": "Âžo\u000180Âť\f8~ Âť\u000f9\u000180Âť\u000e9\u000180 Âť\f8~Âť\n9\f8Âź\f9jÂś\u000f8` Âź\f9nÂťw^Âť\f8\f8 Âź\f9\u000180 ÂťgnÂťptÂž\f9\u000188Âś\u000f8pÂžh\u000180Âžl\f8."
    },
    {
      "m_CutScenID": 10500001,
      "m_CutScenStrID": "LIFETIME_START_NKM_UNIT_C_FREEDOM_AKI",
      "m_bWaitClick": true,
      "m_fWaitTime": 0,
      "m_Face": "UNIT_HATE",
      "m_CharStrID": "AKI_FREEDOM_NULL_NULL",
      "m_Pos": "C",
      "m_Talk_KOREA": "......Âž\f9ZÂť\u000b9^, Âž\r8pÂś\u000185d.",
      "m_fTalkTime": 0.03,
      "m_Talk_USA": "......Âž\f9ZÂť\u000b9^, Âž\r8pÂś\u000185d.",
      "m_Talk_JAPAN": "......Âž\f9ZÂť\u000b9^, Âž\r8pÂś\u000185d."
    },
    {
      "m_CutScenID": 10500001,
      "m_CutScenStrID": "LIFETIME_START_NKM_UNIT_C_FREEDOM_AKI",
      "m_bWaitClick": true,
      "m_fWaitTime": 0,
      "m_CharStrID": "AKI_FREEDOM_NULL_NULL",
      "m_Pos": "C",
      "m_Talk_KOREA": "ÂžYoÂś~\n9Âź\f9\u000180 Âť\u000f9\u000180Âť\u000b9^ Âžo\u000180Âś~ Âť\\gÂž\u000f9dÂžZp Âž\f9^ Âťdp Âś\u000184~Âźl`Âž\r8hÂž\f9ZÂžl\f8?",
      "m_fTalkTime": 0.03,
      "m_Talk_USA": "ÂžYoÂś~\n9Âź\f9\u000180 Âť\u000f9\u000180Âť\u000b9^ Âžo\u000180Âś~ Âť\\gÂž\u000f9dÂžZp Âž\f9^ Âťdp Âś\u000184~Âźl`Âž\r8hÂž\f9ZÂžl\f8?",
      "m_Talk_JAPAN": "ÂžYoÂś~\n9Âź\f9\u000180 Âť\u000f9\u000180Âť\u000b9^ Âžo\u000180Âś~ Âť\\gÂž\u000f9dÂžZp Âž\f9^ Âťdp Âś\u000184~Âźl`Âž\r8hÂž\f9ZÂžl\f8?"
    },
    {
      "m_CutScenID": 10500001,
      "m_CutScenStrID": "LIFETIME_START_NKM_UNIT_C_FREEDOM_AKI",
      "m_bWaitClick": true,
      "m_fWaitTime": 0,
      "m_Face": "UNIT_LAUGH",
      "m_CharStrID": "AKI_FREEDOM_NULL_NULL",
      "m_Pos": "C",
      "m_Crash": 40,
      "m_Talk_KOREA": "ÂžXzÂž\r8uÂť\u000b9j ÂžweÂťz\u000180Âž\u000b9t Âžp\f9ÂťcZÂť\u000e9\u000180 Âť\u000182ZÂťx[ Âťc^ Âť\u000f8ZÂť\u000b8\f8 Âť\u000185ZÂť\u000f8\f9 Âś~kÂžo\n8 Âś\u000f8` Âž\r8\f8Âťn\u000e9 Âž^\u000e8Âś\u000f8\u000e8Âžp\u000184 Âž\r8^ÂžoZ Âś~ÂžidÂžl\f8!",
      "m_fTalkTime": 0.03,
      "m_Talk_USA": "ÂžXzÂž\r8uÂť\u000b9j ÂžweÂťz\u000180Âž\u000b9t Âžp\f9ÂťcZÂť\u000e9\u000180 Âť\u000182ZÂťx[ Âťc^ Âť\u000f8ZÂť\u000b8\f8 Âť\u000185ZÂť\u000f8\f9 Âś~kÂžo\n8 Âś\u000f8` Âž\r8\f8Âťn\u000e9 Âž^\u000e8Âś\u000f8\u000e8Âžp\u000184 Âž\r8^ÂžoZ Âś~ÂžidÂžl\f8!",
      "m_Talk_JAPAN": "ÂžXzÂž\r8uÂť\u000b9j ÂžweÂťz\u000180Âž\u000b9t Âžp\f9ÂťcZÂť\u000e9\u000180 Âť\u000182ZÂťx[ Âťc^ Âť\u000f8ZÂť\u000b8\f8 Âť\u000185ZÂť\u000f8\f9 Âś~kÂžo\n8 Âś\u000f8` Âž\r8\f8Âťn\u000e9 Âž^\u000e8Âś\u000f8\u000e8Âžp\u000184 Âž\r8^ÂžoZ Âś~ÂžidÂžl\f8!"
    },
    {
      "m_CutScenID": 10500001,
      "m_CutScenStrID": "LIFETIME_START_NKM_UNIT_C_FREEDOM_AKI",
      "m_bWaitClick": false,
      "m_fWaitTime": 0,
      "m_bFadeIn": false,
      "m_fFadeTime": 2
    },
    {
      "m_CutScenID": 10500001,
      "m_CutScenStrID": "LIFETIME_START_NKM_UNIT_C_FREEDOM_AKI",
      "m_bWaitClick": false,
      "m_fWaitTime": 0,
      "m_BGFileName": "LIFETIME",
      "m_Face": "UNIT_LAUGH",
      "m_bFadeIn": true,
      "m_fFadeTime": 3,
      "m_StartFXSoundName": "FX_CUTSCEN_DOOR_WOOD",
      "m_CharStrID": "AKI_FREEDOM_NULL_NULL",
      "m_Pos": "C_D"
    },
    {
      "m_CutScenID": 10500001,
      "m_CutScenStrID": "LIFETIME_START_NKM_UNIT_C_FREEDOM_AKI",
      "m_bWaitClick": true,
      "m_fWaitTime": 0,
      "m_StartBGMFileName": "CUTSCENE_HOPE",
      "m_CharStrID": "USER_ADMIN_NULL_NULL",
      "m_Talk_KOREA": "Âť~jÂś~eÂťZt, Âž\f9ZÂźXt Âžhe.",
      "m_fTalkTime": 0.03,
      "m_Talk_USA": "Âť~jÂś~eÂťZt, Âž\f9ZÂźXt Âžhe.",
      "m_Talk_JAPAN": "Âť~jÂś~eÂťZt, Âž\f9ZÂźXt Âžhe."
    },
    {
      "m_CutScenID": 10500001,
      "m_CutScenStrID": "LIFETIME_START_NKM_UNIT_C_FREEDOM_AKI",
      "m_bWaitClick": true,
      "m_fWaitTime": 0,
      "m_Face": "UNIT_SURPRISE",
      "m_CharStrID": "AKI_FREEDOM_NULL_NULL",
      "m_Pos": "C",
      "m_Crash": 100,
      "m_Talk_KOREA": "ÂžiZÂťw^ÂžhcÂś\u000185nÂžwoÂžo\u000180Âž\f9\u000189!",
      "m_fTalkTime": 0.03,
      "m_Talk_USA": "ÂžiZÂťw^ÂžhcÂś\u000185nÂžwoÂžo\u000180Âž\f9\u000189!",
      "m_Talk_JAPAN": "ÂžiZÂťw^ÂžhcÂś\u000185nÂžwoÂžo\u000180Âž\f9\u000189!"
    },
    {
      "m_CutScenID": 10500001,
      "m_CutScenStrID": "LIFETIME_START_NKM_UNIT_C_FREEDOM_AKI",
      "m_bWaitClick": true,
      "m_fWaitTime": 0,
      "m_CharStrID": "AKI_FREEDOM_NULL_NULL",
      "m_Pos": "C",
      "m_Crash": 20,
      "m_Talk_KOREA": "Âť^ZÂť^ZÂť^ZÂť^ZÂś\u000181zÂžZ\u000184Âžl\f8? ÂžizÂś\u000184~ Âť{dÂź\f9jÂť\r9z ÂťgtÂžh\u000180Âžk\f8Âžh\u000180Âžl\f8? Âźj\u000185Âž\u000b9n......!",
      "m_fTalkTime": 0.09,
      "m_Talk_USA": "Âť^ZÂť^ZÂť^ZÂť^ZÂś\u000181zÂžZ\u000184Âžl\f8? ÂžizÂś\u000184~ Âť{dÂź\f9jÂť\r9z ÂťgtÂžh\u000180Âžk\f8Âžh\u000180Âžl\f8? Âźj\u000185Âž\u000b9n......!",
      "m_Talk_JAPAN": "Âť^ZÂť^ZÂť^ZÂť^ZÂś\u000181zÂžZ\u000184Âžl\f8? ÂžizÂś\u000184~ Âť{dÂź\f9jÂť\r9z ÂťgtÂžh\u000180Âžk\f8Âžh\u000180Âžl\f8? Âźj\u000185Âž\u000b9n......!"
    },
    {
      "m_CutScenID": 10500001,
      "m_CutScenStrID": "LIFETIME_START_NKM_UNIT_C_FREEDOM_AKI",
      "m_bWaitClick": true,
      "m_fWaitTime": 0,
      "m_Face": "UNIT_SERIOUS",
      "m_CharStrID": "AKI_FREEDOM_NULL_NULL",
      "m_Pos": "C",
      "m_Crash": 50,
      "m_Talk_KOREA": "Âť\u000b9\u000185Âž\u000b9pÂťcZ ÂžXzÂž\r8uÂť\u000b9jÂžoj Âť\u000182^ÂťqnÂž\\`Âťgo Âť\u000185ZÂť\u000f8\f9ÂžoZ Âť[\u000184ÂťvzÂś\u000f9p?!",
      "m_fTalkTime": 0.09,
      "m_Talk_USA": "Âť\u000b9\u000185Âž\u000b9pÂťcZ ÂžXzÂž\r8uÂť\u000b9jÂžoj Âť\u000182^ÂťqnÂž\\`Âťgo Âť\u000185ZÂť\u000f8\f9ÂžoZ Âť[\u000184ÂťvzÂś\u000f9p?!",
      "m_Talk_JAPAN": "Âť\u000b9\u000185Âž\u000b9pÂťcZ ÂžXzÂž\r8uÂť\u000b9jÂžoj Âť\u000182^ÂťqnÂž\\`Âťgo Âť\u000185ZÂť\u000f8\f9ÂžoZ Âť[\u000184ÂťvzÂś\u000f9p?!"
    },
    {
      "m_CutScenID": 10500001,
      "m_CutScenStrID": "LIFETIME_START_NKM_UNIT_C_FREEDOM_AKI",
      "m_bWaitClick": false,
      "m_fWaitTime": 0,
      "m_CharStrID": "AKI_FREEDOM_NULL_NULL",
      "m_Pos": "C_D"
    },
    {
      "m_CutScenID": 10500001,
      "m_CutScenStrID": "LIFETIME_START_NKM_UNIT_C_FREEDOM_AKI",
      "m_bWaitClick": true,
      "m_fWaitTime": 0,
      "m_CharStrID": "USER_ADMIN_NULL_NULL",
      "m_Talk_KOREA": "......Âś\u000183\u000184Âť\r9~ Âźb\u000184ÂťvzÂź\f9n Âť\u000185ZÂť\u000f8\f9 Âś~kÂžo\n8 Âś\u000180 Âži\\ÂžoZ Âť\u000191dÂťa\f8Âť\r9z, Âž\r8^Âžh\u000180ÂťcZ Âžo\u000180Âť\r9~ ÂžnZÂźijÂź\f9n Âś\u000f9\u000f9Âži\f8 Âž\f9^ Âť\u000f9\u000180Âś\u000180\n8Âź\f9\u000180.",
      "m_fTalkTime": 0.03,
      "m_Talk_USA": "......Âś\u000183\u000184Âť\r9~ Âźb\u000184ÂťvzÂź\f9n Âť\u000185ZÂť\u000f8\f9 Âś~kÂžo\n8 Âś\u000180 Âži\\ÂžoZ Âť\u000191dÂťa\f8Âť\r9z, Âž\r8^Âžh\u000180ÂťcZ Âžo\u000180Âť\r9~ ÂžnZÂźijÂź\f9n Âś\u000f9\u000f9Âži\f8 Âž\f9^ Âť\u000f9\u000180Âś\u000180\n8Âź\f9\u000180.",
      "m_Talk_JAPAN": "......Âś\u000183\u000184Âť\r9~ Âźb\u000184ÂťvzÂź\f9n Âť\u000185ZÂť\u000f8\f9 Âś~kÂžo\n8 Âś\u000180 Âži\\ÂžoZ Âť\u000191dÂťa\f8Âť\r9z, Âž\r8^Âžh\u000180ÂťcZ Âžo\u000180Âť\r9~ ÂžnZÂźijÂź\f9n Âś\u000f9\u000f9Âži\f8 Âž\f9^ Âť\u000f9\u000180Âś\u000180\n8Âź\f9\u000180."
    },
    {
      "m_CutScenID": 10500001,
      "m_CutScenStrID": "LIFETIME_START_NKM_UNIT_C_FREEDOM_AKI",
      "m_bWaitClick": true,
      "m_fWaitTime": 0,
      "m_CharStrID": "AKI_FREEDOM_NULL_NULL",
      "m_Pos": "C",
      "m_Crash": 30,
      "m_Talk_KOREA": "ÂžXzÂž\r8uÂť\u000b9jÂžo\u000180 Âžp\n8Âťu\u000188 Âž\\aÂžj\n8Âť\u000b9tÂś\u000f9pÂžl\f8? Âś\u000183\u000184Âť\r9\u000180 Âťvz Âži\\Âžh\u000180Âžl\f8!",
      "m_fTalkTime": 0.03,
      "m_Talk_USA": "ÂžXzÂž\r8uÂť\u000b9jÂžo\u000180 Âžp\n8Âťu\u000188 Âž\\aÂžj\n8Âť\u000b9tÂś\u000f9pÂžl\f8? Âś\u000183\u000184Âť\r9\u000180 Âťvz Âži\\Âžh\u000180Âžl\f8!",
      "m_Talk_JAPAN": "ÂžXzÂž\r8uÂť\u000b9jÂžo\u000180 Âžp\n8Âťu\u000188 Âž\\aÂžj\n8Âť\u000b9tÂś\u000f9pÂžl\f8? Âś\u000183\u000184Âť\r9\u000180 Âťvz Âži\\Âžh\u000180Âžl\f8!"
    },
    {
      "m_CutScenID": 10500001,
      "m_CutScenStrID": "LIFETIME_START_NKM_UNIT_C_FREEDOM_AKI",
      "m_bWaitClick": true,
      "m_fWaitTime": 0,
      "m_CharStrID": "AKI_FREEDOM_NULL_NULL",
      "m_Pos": "C",
      "m_Talk_KOREA": "Âť\u000182ZÂťx[ Âžo\u000180 Âť~\u000e9 Âžh\u000180Âť\f8jÂś~\n8Âžid Âžp\n8Âź\f9nÂź[` ÂžtZ Âž~\u000e8Âťx[Âś\u000f9ZÂžr` ÂťvzÂž\u000b8tÂź\u000b8\u000184 Âś~kÂžo\n8 Âś\u000184 Âž^\u000e8Âś\u000f8\u000e8 ÂťedÂž[\u000e8ÂžoZ Âś~Âťo\u000188Âś\u000f9pÂžl\f8!",
      "m_fTalkTime": 0.03,
      "m_Talk_USA": "Âť\u000182ZÂťx[ Âžo\u000180 Âť~\u000e9 Âžh\u000180Âť\f8jÂś~\n8Âžid Âžp\n8Âź\f9nÂź[` ÂžtZ Âž~\u000e8Âťx[Âś\u000f9ZÂžr` ÂťvzÂž\u000b8tÂź\u000b8\u000184 Âś~kÂžo\n8 Âś\u000184 Âž^\u000e8Âś\u000f8\u000e8 ÂťedÂž[\u000e8ÂžoZ Âś~Âťo\u000188Âś\u000f9pÂžl\f8!",
      "m_Talk_JAPAN": "Âť\u000182ZÂťx[ Âžo\u000180 Âť~\u000e9 Âžh\u000180Âť\f8jÂś~\n8Âžid Âžp\n8Âź\f9nÂź[` ÂžtZ Âž~\u000e8Âťx[Âś\u000f9ZÂžr` ÂťvzÂž\u000b8tÂź\u000b8\u000184 Âś~kÂžo\n8 Âś\u000184 Âž^\u000e8Âś\u000f8\u000e8 ÂťedÂž[\u000e8ÂžoZ Âś~Âťo\u000188Âś\u000f9pÂžl\f8!"
    },
    {
      "m_CutScenID": 10500001,
      "m_CutScenStrID": "LIFETIME_START_NKM_UNIT_C_FREEDOM_AKI",
      "m_bWaitClick": false,
      "m_fWaitTime": 0,
      "m_CharStrID": "AKI_FREEDOM_NULL_NULL",
      "m_Pos": "C_D"
    },
    {
      "m_CutScenID": 10500001,
      "m_CutScenStrID": "LIFETIME_START_NKM_UNIT_C_FREEDOM_AKI",
      "m_bWaitClick": true,
      "m_fWaitTime": 0,
      "m_CharStrID": "USER_ADMIN_NULL_NULL",
      "m_Talk_KOREA": "ÂťZ^Âťz\u000180 Âžo\u000188Âť~\u000e9Âžp\n9Âžo\u000184 Âž~\u000e9Âś~\n9Âžo\u000180Âťo\u000188 Âžh\u000180Âť\f8\f8ÂžZnÂť\u000182\n8ÂźZ~ Âžp\f9Âžp\f9Âź\f9\u000180 ÂžtjÂž\f9\u000188 Âź\f9pÂžw\n8 Âś~dÂžo\u000180 Âž\f9^ Âž\r8qÂź\r8^ÂťZtÂťw`......",
      "m_fTalkTime": 0.03,
      "m_Talk_USA": "ÂťZ^Âťz\u000180 Âžo\u000188Âť~\u000e9Âžp\n9Âžo\u000184 Âž~\u000e9Âś~\n9Âžo\u000180Âťo\u000188 Âžh\u000180Âť\f8\f8ÂžZnÂť\u000182\n8ÂźZ~ Âžp\f9Âžp\f9Âź\f9\u000180 ÂžtjÂž\f9\u000188 Âź\f9pÂžw\n8 Âś~dÂžo\u000180 Âž\f9^ Âž\r8qÂź\r8^ÂťZtÂťw`......",
      "m_Talk_JAPAN": "ÂťZ^Âťz\u000180 Âžo\u000188Âť~\u000e9Âžp\n9Âžo\u000184 Âž~\u000e9Âś~\n9Âžo\u000180Âťo\u000188 Âžh\u000180Âť\f8\f8ÂžZnÂť\u000182\n8ÂźZ~ Âžp\f9Âžp\f9Âź\f9\u000180 ÂžtjÂž\f9\u000188 Âź\f9pÂžw\n8 Âś~dÂžo\u000180 Âž\f9^ Âž\r8qÂź\r8^ÂťZtÂťw`......"
    },
    {
      "m_CutScenID": 10500001,
      "m_CutScenStrID": "LIFETIME_START_NKM_UNIT_C_FREEDOM_AKI",
      "m_bWaitClick": true,
      "m_fWaitTime": 0,
      "m_CharStrID": "USER_ADMIN_NULL_NULL",
      "m_Talk_KOREA": "Âžl~ÂžZp ÂťX\u000180Âś~\n8 Âž\r8dÂťZt ÂžXzÂž\r8uÂť\u000b9jÂžo\u000188ÂžZ\u000184.",
      "m_fTalkTime": 0.03,
      "m_Talk_USA": "Âžl~ÂžZp ÂťX\u000180Âś~\n8 Âž\r8dÂťZt ÂžXzÂž\r8uÂť\u000b9jÂžo\u000188ÂžZ\u000184.",
      "m_Talk_JAPAN": "Âžl~ÂžZp ÂťX\u000180Âś~\n8 Âž\r8dÂťZt ÂžXzÂž\r8uÂť\u000b9jÂžo\u000188ÂžZ\u000184."
    },
    {
      "m_CutScenID": 10500001,
      "m_CutScenStrID": "LIFETIME_START_NKM_UNIT_C_FREEDOM_AKI",
      "m_bWaitClick": true,
      "m_fWaitTime": 0,
      "m_Face": "UNIT_SURPRISE",
      "m_CharStrID": "AKI_FREEDOM_NULL_NULL",
      "m_Pos": "C",
      "m_Talk_KOREA": "......Âžp\n8Âźoz ÂžXzÂž\r8uÂť\u000b9j Âž\f9\u000188Âť~jÂťcZÂžs\u000188Âź\f9jÂž[\u000e8Âžh\u000180Âžl\f8?",
      "m_fTalkTime": 0.03,
      "m_Talk_USA": "......Âžp\n8Âźoz ÂžXzÂž\r8uÂť\u000b9j Âž\f9\u000188Âť~jÂťcZÂžs\u000188Âź\f9jÂž[\u000e8Âžh\u000180Âžl\f8?",
      "m_Talk_JAPAN": "......Âžp\n8Âźoz ÂžXzÂž\r8uÂť\u000b9j Âž\f9\u000188Âť~jÂťcZÂžs\u000188Âź\f9jÂž[\u000e8Âžh\u000180Âžl\f8?"
    },
    {
      "m_CutScenID": 10500001,
      "m_CutScenStrID": "LIFETIME_START_NKM_UNIT_C_FREEDOM_AKI",
      "m_bWaitClick": false,
      "m_fWaitTime": 0,
      "m_bFadeIn": false,
      "m_fFadeTime": 1
    },
    {
      "m_CutScenID": 10500001,
      "m_CutScenStrID": "LIFETIME_START_NKM_UNIT_C_FREEDOM_AKI",
      "m_bWaitClick": false,
      "m_fWaitTime": 0,
      "m_BGFileName": "LIFETIME",
      "m_bFadeIn": true,
      "m_fFadeTime": 1
    },
    {
      "m_CutScenID": 10500001,
      "m_CutScenStrID": "LIFETIME_START_NKM_UNIT_C_FREEDOM_AKI",
      "m_bWaitClick": true,
      "m_fWaitTime": 0,
      "m_Face": "UNIT_LAUGH",
      "m_CharStrID": "AKI_FREEDOM_NULL_NULL",
      "m_Pos": "C",
      "m_Talk_KOREA": "Âž\f9Z, Âž\f9ZÂź\f9j, Âž\f9ZÂź\f9jÂź\f9j...... Âś\u000183\u000184Âť\r9zÂť\u000b9^Âś\u000185` Âžp\f9Âž\u000f8\u000180Âś~\n8 Âž\f9`ÂťptÂžw\n8Âť\u000e9\u000180 Âś\u000f9tÂť\r8\n8Âź\f9jÂť\u000b9^Âś\u000185` Âž^\u000e8Âś\u000184~Âž\u000b9nÂťptÂś\u000f9p......",
      "m_fTalkTime": 0.03,
      "m_Talk_USA": "Âž\f9Z, Âž\f9ZÂź\f9j, Âž\f9ZÂź\f9jÂź\f9j...... Âś\u000183\u000184Âť\r9zÂť\u000b9^Âś\u000185` Âžp\f9Âž\u000f8\u000180Âś~\n8 Âž\f9`ÂťptÂžw\n8Âť\u000e9\u000180 Âś\u000f9tÂť\r8\n8Âź\f9jÂť\u000b9^Âś\u000185` Âž^\u000e8Âś\u000184~Âž\u000b9nÂťptÂś\u000f9p......",
      "m_Talk_JAPAN": "Âž\f9Z, Âž\f9ZÂź\f9j, Âž\f9ZÂź\f9jÂź\f9j...... Âś\u000183\u000184Âť\r9zÂť\u000b9^Âś\u000185` Âžp\f9Âž\u000f8\u000180Âś~\n8 Âž\f9`ÂťptÂžw\n8Âť\u000e9\u000180 Âś\u000f9tÂť\r8\n8Âź\f9jÂť\u000b9^Âś\u000185` Âž^\u000e8Âś\u000184~Âž\u000b9nÂťptÂś\u000f9p......"
    },
    {
      "m_CutScenID": 10500001,
      "m_CutScenStrID": "LIFETIME_START_NKM_UNIT_C_FREEDOM_AKI",
      "m_bWaitClick": true,
      "m_fWaitTime": 0,
      "m_CharStrID": "AKI_FREEDOM_NULL_NULL",
      "m_Pos": "C",
      "m_Crash": 15,
      "m_Talk_KOREA": "ÂžwZÂžv_ ÂťwdÂž\f8\n8Âź\f9jÂž\u000b9nÂžw\n8 Âś\u000183\u000184Âť\r8zÂžh\u000180Âžl\f8. Âž\f9ZÂś\u000185` Âžpn Âťwd Âť\u000b9t Âť\\aÂť\u000b9\u000180Âžo\u000184 Âś~ Âž\f9ZÂž\u000b9nÂžsp? ÂťZtÂžid?",
      "m_fTalkTime": 0.03,
      "m_Talk_USA": "ÂžwZÂžv_ ÂťwdÂž\f8\n8Âź\f9jÂž\u000b9nÂžw\n8 Âś\u000183\u000184Âť\r8zÂžh\u000180Âžl\f8. Âž\f9ZÂś\u000185` Âžpn Âťwd Âť\u000b9t Âť\\aÂť\u000b9\u000180Âžo\u000184 Âś~ Âž\f9ZÂž\u000b9nÂžsp? ÂťZtÂžid?",
      "m_Talk_JAPAN": "ÂžwZÂžv_ ÂťwdÂž\f8\n8Âź\f9jÂž\u000b9nÂžw\n8 Âś\u000183\u000184Âť\r8zÂžh\u000180Âžl\f8. Âž\f9ZÂś\u000185` Âžpn Âťwd Âť\u000b9t Âť\\aÂť\u000b9\u000180Âžo\u000184 Âś~ Âž\f9ZÂž\u000b9nÂžsp? ÂťZtÂžid?"
    },
    {
      "m_CutScenID": 10500001,
      "m_CutScenStrID": "LIFETIME_START_NKM_UNIT_C_FREEDOM_AKI",
      "m_bWaitClick": false,
      "m_fWaitTime": 0,
      "m_CharStrID": "AKI_FREEDOM_NULL_NULL",
      "m_Pos": "C_D"
    },
    {
      "m_CutScenID": 10500001,
      "m_CutScenStrID": "LIFETIME_START_NKM_UNIT_C_FREEDOM_AKI",
      "m_bWaitClick": true,
      "m_fWaitTime": 0,
      "m_CharStrID": "USER_ADMIN_NULL_NULL",
      "m_Talk_KOREA": "ÂťedÂťwdÂź\f9p Âś\u000f8Y Âži\\Âžo\u000180 ÂžwZÂť\u000b9\u000180Âžn\u000188Âťqn ÂťgtÂťp\u000184ÂťZt.",
      "m_fTalkTime": 0.03,
      "m_Talk_USA": "ÂťedÂťwdÂź\f9p Âś\u000f8Y Âži\\Âžo\u000180 ÂžwZÂť\u000b9\u000180Âžn\u000188Âťqn ÂťgtÂťp\u000184ÂťZt.",
      "m_Talk_JAPAN": "ÂťedÂťwdÂź\f9p Âś\u000f8Y Âži\\Âžo\u000180 ÂžwZÂť\u000b9\u000180Âžn\u000188Âťqn ÂťgtÂťp\u000184ÂťZt."
    },
    {
      "m_CutScenID": 10500001,
      "m_CutScenStrID": "LIFETIME_START_NKM_UNIT_C_FREEDOM_AKI",
      "m_bWaitClick": true,
      "m_fWaitTime": 0,
      "m_Face": "UNIT_HATE",
      "m_CharStrID": "AKI_FREEDOM_NULL_NULL",
      "m_Pos": "C",
      "m_Crash": 40,
      "m_Talk_KOREA": "Âž\u000f8\u000180Âžis......",
      "m_fTalkTime": 0.03,
      "m_Talk_USA": "Âž\u000f8\u000180Âžis......",
      "m_Talk_JAPAN": "Âž\u000f8\u000180Âžis......"
    },
    {
      "m_CutScenID": 10500001,
      "m_CutScenStrID": "LIFETIME_START_NKM_UNIT_C_FREEDOM_AKI",
      "m_bWaitClick": false,
      "m_fWaitTime": 0,
      "m_CharStrID": "AKI_FREEDOM_NULL_NULL",
      "m_Pos": "C_D"
    },
    {
      "m_CutScenID": 10500001,
      "m_CutScenStrID": "LIFETIME_START_NKM_UNIT_C_FREEDOM_AKI",
      "m_bWaitClick": true,
      "m_fWaitTime": 0,
      "m_CharStrID": "USER_ADMIN_NULL_NULL",
      "m_Talk_KOREA": "Âťz\u000188Âťqp Âś\u000183\u000184Âťp]Âť\u000b9tÂś\u000f9p Âž\r8dÂťZtÂžidÂś\u000f8` Âť\u000182^Âžo\u000180Âžo\u000181ÂžoZ Âžt\n8Âť\u000b9tÂś~ÂťXj Âź\f9p ÂžYoÂś~\n9Âžo\n8 Âži\\Âť\u000b9tÂťZt.",
      "m_fTalkTime": 0.03,
      "m_Talk_USA": "Âťz\u000188Âťqp Âś\u000183\u000184Âťp]Âť\u000b9tÂś\u000f9p Âž\r8dÂťZtÂžidÂś\u000f8` Âť\u000182^Âžo\u000180Âžo\u000181ÂžoZ Âžt\n8Âť\u000b9tÂś~ÂťXj Âź\f9p ÂžYoÂś~\n9Âžo\n8 Âži\\Âť\u000b9tÂťZt.",
      "m_Talk_JAPAN": "Âťz\u000188Âťqp Âś\u000183\u000184Âťp]Âť\u000b9tÂś\u000f9p Âž\r8dÂťZtÂžidÂś\u000f8` Âť\u000182^Âžo\u000180Âžo\u000181ÂžoZ Âžt\n8Âť\u000b9tÂś~ÂťXj Âź\f9p ÂžYoÂś~\n9Âžo\n8 Âži\\Âť\u000b9tÂťZt."
    },
    {
      "m_CutScenID": 10500001,
      "m_CutScenStrID": "LIFETIME_START_NKM_UNIT_C_FREEDOM_AKI",
      "m_bWaitClick": true,
      "m_fWaitTime": 0,
      "m_CharStrID": "USER_ADMIN_NULL_NULL",
      "m_Talk_KOREA": "Âžw\n9ÂžmdÂžo\u000180 ÂźoeÂž\u000b9z Âžr\n8 Âźf^ÂžoZ Âž^j Âž\r8^Âžw\n8, Âž\f9^ Âś\u000183\u000184Âť\r9zÂťXj? Âź\f9jÂź\f9jÂź\f9j.",
      "m_fTalkTime": 0.03,
      "m_Talk_USA": "Âžw\n9ÂžmdÂžo\u000180 ÂźoeÂž\u000b9z Âžr\n8 Âźf^ÂžoZ Âž^j Âž\r8^Âžw\n8, Âž\f9^ Âś\u000183\u000184Âť\r9zÂťXj? Âź\f9jÂź\f9jÂź\f9j.",
      "m_Talk_JAPAN": "Âžw\n9ÂžmdÂžo\u000180 ÂźoeÂž\u000b9z Âžr\n8 Âźf^ÂžoZ Âž^j Âž\r8^Âžw\n8, Âž\f9^ Âś\u000183\u000184Âť\r9zÂťXj? Âź\f9jÂź\f9jÂź\f9j."
    },
    {
      "m_CutScenID": 10500001,
      "m_CutScenStrID": "LIFETIME_START_NKM_UNIT_C_FREEDOM_AKI",
      "m_bWaitClick": true,
      "m_fWaitTime": 0,
      "m_Face": "UNIT_SURPRISE",
      "m_CharStrID": "AKI_FREEDOM_NULL_NULL",
      "m_Pos": "C",
      "m_Talk_KOREA": "ÂťZt?",
      "m_fTalkTime": 0.03,
      "m_Talk_USA": "ÂťZt?",
      "m_Talk_JAPAN": "ÂťZt?"
    },
    {
      "m_CutScenID": 10500001,
      "m_CutScenStrID": "LIFETIME_START_NKM_UNIT_C_FREEDOM_AKI",
      "m_bWaitClick": true,
      "m_fWaitTime": 0,
      "m_Face": "UNIT_IDLE",
      "m_CharStrID": "AKI_FREEDOM_NULL_NULL",
      "m_Pos": "C",
      "m_Talk_KOREA": "Âž\f9Z, Âś\u000183\u000184Âś\u000f8`, Âťw\r8Âž\f9ZÂžl\f8! Âť\u000b9\u000185Âži~Âź\r8^ Âś\u000183\u000184Âťp]Âžsp!",
      "m_fTalkTime": 0.03,
      "m_Talk_USA": "Âž\f9Z, Âś\u000183\u000184Âś\u000f8`, Âťw\r8Âž\f9ZÂžl\f8! Âť\u000b9\u000185Âži~Âź\r8^ Âś\u000183\u000184Âťp]Âžsp!",
      "m_Talk_JAPAN": "Âž\f9Z, Âś\u000183\u000184Âś\u000f8`, Âťw\r8Âž\f9ZÂžl\f8! Âť\u000b9\u000185Âži~Âź\r8^ Âś\u000183\u000184Âťp]Âžsp!"
    },
    {
      "m_CutScenID": 10500001,
      "m_CutScenStrID": "LIFETIME_START_NKM_UNIT_C_FREEDOM_AKI",
      "m_bWaitClick": true,
      "m_fWaitTime": 0,
      "m_CharStrID": "AKI_FREEDOM_NULL_NULL",
      "m_Pos": "C",
      "m_Talk_KOREA": "Âś\u000180\n8ÂťvzÂť\u000182\n8 Âź\f9jÂťXj Âž\f8\u000e8ÂťcZ Âť\u000182ZÂťx[ Âť}\u000184Âź`[ÂžoZ Âť`\n8Âś~\n8Âťqn Âžw\n9Âžmd Âžp\f9Âť\u000f9\u000180 Âź\f9nÂťed Âť\u000f8^Âžo\n8 Âť\u000185\u000188Âťc`Âťp\u000184ÂžoZ Âś~Âťo\u000188Âś\u000f9pÂžl\f8!",
      "m_fTalkTime": 0.03,
      "m_Talk_USA": "Âś\u000180\n8ÂťvzÂť\u000182\n8 Âź\f9jÂťXj Âž\f8\u000e8ÂťcZ Âť\u000182ZÂťx[ Âť}\u000184Âź`[ÂžoZ Âť`\n8Âś~\n8Âťqn Âžw\n9Âžmd Âžp\f9Âť\u000f9\u000180 Âź\f9nÂťed Âť\u000f8^Âžo\n8 Âť\u000185\u000188Âťc`Âťp\u000184ÂžoZ Âś~Âťo\u000188Âś\u000f9pÂžl\f8!",
      "m_Talk_JAPAN": "Âś\u000180\n8ÂťvzÂť\u000182\n8 Âź\f9jÂťXj Âž\f8\u000e8ÂťcZ Âť\u000182ZÂťx[ Âť}\u000184Âź`[ÂžoZ Âť`\n8Âś~\n8Âťqn Âžw\n9Âžmd Âžp\f9Âť\u000f9\u000180 Âź\f9nÂťed Âť\u000f8^Âžo\n8 Âť\u000185\u000188Âťc`Âťp\u000184ÂžoZ Âś~Âťo\u000188Âś\u000f9pÂžl\f8!"
    },
    {
      "m_CutScenID": 10500001,
      "m_CutScenStrID": "LIFETIME_START_NKM_UNIT_C_FREEDOM_AKI",
      "m_bWaitClick": false,
      "m_fWaitTime": 0,
      "m_CharStrID": "AKI_FREEDOM_NULL_NULL",
      "m_Pos": "C_D"
    },
    {
      "m_CutScenID": 10500001,
      "m_CutScenStrID": "LIFETIME_START_NKM_UNIT_C_FREEDOM_AKI",
      "m_bWaitClick": true,
      "m_fWaitTime": 0,
      "m_CharStrID": "USER_ADMIN_NULL_NULL",
      "m_Talk_KOREA": "Âž\r8d, Âť^^Âś~dÂž\f9Z ÂžtZ Âź[`Âť\u000b9^ Âžr[Âž\u000b9pÂś\u000f9ZÂž\f9\u000189ÂžoZ Âťw\u000186ÂťcZÂťqo Âź\f9jÂžw\n8.",
      "m_fTalkTime": 0.03,
      "m_Talk_USA": "Âž\r8d, Âť^^Âś~dÂž\f9Z ÂžtZ Âź[`Âť\u000b9^ Âžr[Âž\u000b9pÂś\u000f9ZÂž\f9\u000189ÂžoZ Âťw\u000186ÂťcZÂťqo Âź\f9jÂžw\n8.",
      "m_Talk_JAPAN": "Âž\r8d, Âť^^Âś~dÂž\f9Z ÂžtZ Âź[`Âť\u000b9^ Âžr[Âž\u000b9pÂś\u000f9ZÂž\f9\u000189ÂžoZ Âťw\u000186ÂťcZÂťqo Âź\f9jÂžw\n8."
    },
    {
      "m_CutScenID": 10500001,
      "m_CutScenStrID": "LIFETIME_START_NKM_UNIT_C_FREEDOM_AKI",
      "m_bWaitClick": true,
      "m_fWaitTime": 0,
      "m_Face": "UNIT_HATE",
      "m_CharStrID": "AKI_FREEDOM_NULL_NULL",
      "m_Pos": "C",
      "m_Crash": 40,
      "m_Talk_KOREA": "Âž\f9ZÂž\f9i?! Âťjd Âś~ÂžwgÂťwdÂžo\u000180Âž\f9\u000188!",
      "m_fTalkTime": 0.03,
      "m_Talk_USA": "Âž\f9ZÂž\f9i?! Âťjd Âś~ÂžwgÂťwdÂžo\u000180Âž\f9\u000188!",
      "m_Talk_JAPAN": "Âž\f9ZÂž\f9i?! Âťjd Âś~ÂžwgÂťwdÂžo\u000180Âž\f9\u000188!"
    },
    {
      "m_CutScenID": 10500001,
      "m_CutScenStrID": "LIFETIME_START_NKM_UNIT_C_FREEDOM_AKI",
      "m_bWaitClick": true,
      "m_fWaitTime": 0,
      "m_Face": "UNIT_HATE",
      "m_CharStrID": "AKI_FREEDOM_NULL_NULL",
      "m_Pos": "C",
      "m_Crash": 20,
      "m_Talk_KOREA": "ÂžXzÂž\r8uÂť\u000b9jÂžo\n8 Âžp^ Âť\\\n8Âťpt Âť\u000e8\u000185Âť\u000b8\f8 Âś\u000f8` Âś\u000183\u000184Âťp]Âś\u000f8` Âž\r8zÂť~`Âžn\u000188ÂžZ\u000184Âžl\f8?!",
      "m_fTalkTime": 0.03,
      "m_Talk_USA": "ÂžXzÂž\r8uÂť\u000b9jÂžo\n8 Âžp^ Âť\\\n8Âťpt Âť\u000e8\u000185Âť\u000b8\f8 Âś\u000f8` Âś\u000183\u000184Âťp]Âś\u000f8` Âž\r8zÂť~`Âžn\u000188ÂžZ\u000184Âžl\f8?!",
      "m_Talk_JAPAN": "ÂžXzÂž\r8uÂť\u000b9jÂžo\n8 Âžp^ Âť\\\n8Âťpt Âť\u000e8\u000185Âť\u000b8\f8 Âś\u000f8` Âś\u000183\u000184Âťp]Âś\u000f8` Âž\r8zÂť~`Âžn\u000188ÂžZ\u000184Âžl\f8?!"
    },
    {
      "m_CutScenID": 10500001,
      "m_CutScenStrID": "LIFETIME_START_NKM_UNIT_C_FREEDOM_AKI",
      "m_bWaitClick": false,
      "m_fWaitTime": 0,
      "m_CharStrID": "AKI_FREEDOM_NULL_NULL",
      "m_Pos": "C_D"
    },
    {
      "m_CutScenID": 10500001,
      "m_CutScenStrID": "LIFETIME_START_NKM_UNIT_C_FREEDOM_AKI",
      "m_bWaitClick": true,
      "m_fWaitTime": 0,
      "m_CharStrID": "USER_ADMIN_NULL_NULL",
      "m_Talk_KOREA": "Âś\u000183\u000184Âťvz Âž\r8zÂť}\u000184Âť\u000b8\f8 Âži\\ÂťZtÂťw`......",
      "m_fTalkTime": 0.03,
      "m_Talk_USA": "Âś\u000183\u000184Âťvz Âž\r8zÂť}\u000184Âť\u000b8\f8 Âži\\ÂťZtÂťw`......",
      "m_Talk_JAPAN": "Âś\u000183\u000184Âťvz Âž\r8zÂť}\u000184Âť\u000b8\f8 Âži\\ÂťZtÂťw`......"
    },
    {
      "m_CutScenID": 10500001,
      "m_CutScenStrID": "LIFETIME_START_NKM_UNIT_C_FREEDOM_AKI",
      "m_bWaitClick": true,
      "m_fWaitTime": 0,
      "m_CharStrID": "USER_ADMIN_NULL_NULL",
      "m_Talk_KOREA": "Âžs\u000188Âť\u000b8\f8 Âžm\f8Âś\u000184_ Âž\f9ZÂś\u000185oÂžw\n8 Âž\f9\u000b8ÂžoZ Âťw`Âź\n9\u000188 Âť\\\n8Âťpt Âť\u000e8\u000185Âžh\u000180Âž\f9\u000188Âžw\n8 Âžh\u000180Âž\u000e9`Âś\u000f8pÂťXj.",
      "m_fTalkTime": 0.03,
      "m_Talk_USA": "Âžs\u000188Âť\u000b8\f8 Âžm\f8Âś\u000184_ Âž\f9ZÂś\u000185oÂžw\n8 Âž\f9\u000b8ÂžoZ Âťw`Âź\n9\u000188 Âť\\\n8Âťpt Âť\u000e8\u000185Âžh\u000180Âž\f9\u000188Âžw\n8 Âžh\u000180Âž\u000e9`Âś\u000f8pÂťXj.",
      "m_Talk_JAPAN": "Âžs\u000188Âť\u000b8\f8 Âžm\f8Âś\u000184_ Âž\f9ZÂś\u000185oÂžw\n8 Âž\f9\u000b8ÂžoZ Âťw`Âź\n9\u000188 Âť\\\n8Âťpt Âť\u000e8\u000185Âžh\u000180Âž\f9\u000188Âžw\n8 Âžh\u000180Âž\u000e9`Âś\u000f8pÂťXj."
    },
    {
      "m_CutScenID": 10500001,
      "m_CutScenStrID": "LIFETIME_START_NKM_UNIT_C_FREEDOM_AKI",
      "m_bWaitClick": true,
      "m_fWaitTime": 0,
      "m_CharStrID": "AKI_FREEDOM_NULL_NULL",
      "m_Pos": "C",
      "m_Crash": 40,
      "m_Talk_KOREA": "ÂťwdÂž\f8\n8Âžo\u000180 ÂťZ^Âťz\u000180Âź\f9jÂž\u000b9nÂťZtÂžl\f8, ÂžvoÂťwd!?",
      "m_fTalkTime": 0.03,
      "m_Talk_USA": "ÂťwdÂž\f8\n8Âžo\u000180 ÂťZ^Âťz\u000180Âź\f9jÂž\u000b9nÂťZtÂžl\f8, ÂžvoÂťwd!?",
      "m_Talk_JAPAN": "ÂťwdÂž\f8\n8Âžo\u000180 ÂťZ^Âťz\u000180Âź\f9jÂž\u000b9nÂťZtÂžl\f8, ÂžvoÂťwd!?"
    },
    {
      "m_CutScenID": 10500001,
      "m_CutScenStrID": "LIFETIME_START_NKM_UNIT_C_FREEDOM_AKI",
      "m_bWaitClick": false,
      "m_fWaitTime": 0,
      "m_CharStrID": "AKI_FREEDOM_NULL_NULL",
      "m_Pos": "C_D"
    },
    {
      "m_CutScenID": 10500001,
      "m_CutScenStrID": "LIFETIME_START_NKM_UNIT_C_FREEDOM_AKI",
      "m_bWaitClick": true,
      "m_fWaitTime": 0,
      "m_CharStrID": "USER_ADMIN_NULL_NULL",
      "m_Talk_KOREA": "ÂźodÂžo`. Âś\u000183\u000184 Âť~jÂžoeÂžoZ Âť\u000f9\u000180Âť\u000b9^ ÂťX\u000180Âś~\n8 ÂťZ^Âťz\u000180 ÂžZsÂť\u000182\n8Âťu\u000180Âś\u000f8` ÂžpnÂž\f9^Âź\f9n Âś\u000f8Y Âś~kÂś\u000181~.",
      "m_fTalkTime": 0.03,
      "m_Talk_USA": "ÂźodÂžo`. Âś\u000183\u000184 Âť~jÂžoeÂžoZ Âť\u000f9\u000180Âť\u000b9^ ÂťX\u000180Âś~\n8 ÂťZ^Âťz\u000180 ÂžZsÂť\u000182\n8Âťu\u000180Âś\u000f8` ÂžpnÂž\f9^Âź\f9n Âś\u000f8Y Âś~kÂś\u000181~.",
      "m_Talk_JAPAN": "ÂźodÂžo`. Âś\u000183\u000184 Âť~jÂžoeÂžoZ Âť\u000f9\u000180Âť\u000b9^ ÂťX\u000180Âś~\n8 ÂťZ^Âťz\u000180 ÂžZsÂť\u000182\n8Âťu\u000180Âś\u000f8` ÂžpnÂž\f9^Âź\f9n Âś\u000f8Y Âś~kÂś\u000181~."
    },
    {
      "m_CutScenID": 10500001,
      "m_CutScenStrID": "LIFETIME_START_NKM_UNIT_C_FREEDOM_AKI",
      "m_bWaitClick": true,
      "m_fWaitTime": 0,
      "m_Face": "UNIT_PRIDE",
      "m_CharStrID": "AKI_FREEDOM_NULL_NULL",
      "m_Pos": "C",
      "m_Talk_KOREA": "Âť\u000b9\u000185Âži~Âź\f9jÂžsp. Âžr[Âž\u000b9pÂś\u000f9ZÂž\f9\u000189Âžo\u000180Âť\u000e9\u000180 Âžw\n8Âś\u000184^Âś\u000185`Âžw\n8Âť\u000f9\u000180Âť\u000b9t Âťa\f8 ÂźjZÂž\r8uÂžid ÂťwbÂžo\u000180 ÂťXjÂś~\n8Âž\f9\u000188 Âź\f9jÂž\r8hÂž\f9ZÂžl\f8?",
      "m_fTalkTime": 0.03,
      "m_Talk_USA": "Âť\u000b9\u000185Âži~Âź\f9jÂžsp. Âžr[Âž\u000b9pÂś\u000f9ZÂž\f9\u000189Âžo\u000180Âť\u000e9\u000180 Âžw\n8Âś\u000184^Âś\u000185`Âžw\n8Âť\u000f9\u000180Âť\u000b9t Âťa\f8 ÂźjZÂž\r8uÂžid ÂťwbÂžo\u000180 ÂťXjÂś~\n8Âž\f9\u000188 Âź\f9jÂž\r8hÂž\f9ZÂžl\f8?",
      "m_Talk_JAPAN": "Âť\u000b9\u000185Âži~Âź\f9jÂžsp. Âžr[Âž\u000b9pÂś\u000f9ZÂž\f9\u000189Âžo\u000180Âť\u000e9\u000180 Âžw\n8Âś\u000184^Âś\u000185`Âžw\n8Âť\u000f9\u000180Âť\u000b9t Âťa\f8 ÂźjZÂž\r8uÂžid ÂťwbÂžo\u000180 ÂťXjÂś~\n8Âž\f9\u000188 Âź\f9jÂž\r8hÂž\f9ZÂžl\f8?"
    },
    {
      "m_CutScenID": 10500001,
      "m_CutScenStrID": "LIFETIME_START_NKM_UNIT_C_FREEDOM_AKI",
      "m_bWaitClick": true,
      "m_fWaitTime": 0,
      "m_CharStrID": "AKI_FREEDOM_NULL_NULL",
      "m_Pos": "C",
      "m_Talk_KOREA": "Âžpn Âž\u000b9pÂť[dÂś\u000f9\u000188Âť\u000b8\f8 2Âś\u000180eÂť[Z Âžp\f9ÂťcZ ÂťckÂťh\u000e8Âžh\u000180Âžp\u000184 Âž\r8^Âž\u000b8\u000181Âť\u000b9^Âť\u000b9t. ÂźmiÂźmiÂźmi.",
      "m_fTalkTime": 0.03,
      "m_Talk_USA": "Âžpn Âž\u000b9pÂť[dÂś\u000f9\u000188Âť\u000b8\f8 2Âś\u000180eÂť[Z Âžp\f9ÂťcZ ÂťckÂťh\u000e8Âžh\u000180Âžp\u000184 Âž\r8^Âž\u000b8\u000181Âť\u000b9^Âť\u000b9t. ÂźmiÂźmiÂźmi.",
      "m_Talk_JAPAN": "Âžpn Âž\u000b9pÂť[dÂś\u000f9\u000188Âť\u000b8\f8 2Âś\u000180eÂť[Z Âžp\f9ÂťcZ ÂťckÂťh\u000e8Âžh\u000180Âžp\u000184 Âž\r8^Âž\u000b8\u000181Âť\u000b9^Âť\u000b9t. ÂźmiÂźmiÂźmi."
    },
    {
      "m_CutScenID": 10500001,
      "m_CutScenStrID": "LIFETIME_START_NKM_UNIT_C_FREEDOM_AKI",
      "m_bWaitClick": false,
      "m_fWaitTime": 0,
      "m_CharStrID": "AKI_FREEDOM_NULL_NULL",
      "m_Pos": "C_D"
    },
    {
      "m_CutScenID": 10500001,
      "m_CutScenStrID": "LIFETIME_START_NKM_UNIT_C_FREEDOM_AKI",
      "m_bWaitClick": true,
      "m_fWaitTime": 0,
      "m_CharStrID": "USER_ADMIN_NULL_NULL",
      "m_Talk_KOREA": "Âžo\u000180Âť\u000f8^ Âžo\u000188ÂžoZ Âś\u000f9ZÂś\u000184~Âťqn Âť\u000182ZÂť~nÂź\f9\u000180 Âžs\u000188Âť\u000e9\u000180 ÂťX\u000180 Âť\u000185ZÂž\r8uÂžoj Âž~\u000189Âži[ Âť[\u000184Âź\f9jÂžl~Âťo\u000188ÂťcZ Âž\f9`Âťpt Âžs\u000188ÂťptÂś\u000f9p Âźh^Âť\u000b8\f8Âťa~......",
      "m_fTalkTime": 0.03,
      "m_Talk_USA": "Âžo\u000180Âť\u000f8^ Âžo\u000188ÂžoZ Âś\u000f9ZÂś\u000184~Âťqn Âť\u000182ZÂť~nÂź\f9\u000180 Âžs\u000188Âť\u000e9\u000180 ÂťX\u000180 Âť\u000185ZÂž\r8uÂžoj Âž~\u000189Âži[ Âť[\u000184Âź\f9jÂžl~Âťo\u000188ÂťcZ Âž\f9`Âťpt Âžs\u000188ÂťptÂś\u000f9p Âźh^Âť\u000b8\f8Âťa~......",
      "m_Talk_JAPAN": "Âžo\u000180Âť\u000f8^ Âžo\u000188ÂžoZ Âś\u000f9ZÂś\u000184~Âťqn Âť\u000182ZÂť~nÂź\f9\u000180 Âžs\u000188Âť\u000e9\u000180 ÂťX\u000180 Âť\u000185ZÂž\r8uÂžoj Âž~\u000189Âži[ Âť[\u000184Âź\f9jÂžl~Âťo\u000188ÂťcZ Âž\f9`Âťpt Âžs\u000188ÂťptÂś\u000f9p Âźh^Âť\u000b8\f8Âťa~......"
    },
    {
      "m_CutScenID": 10500001,
      "m_CutScenStrID": "LIFETIME_START_NKM_UNIT_C_FREEDOM_AKI",
      "m_bWaitClick": true,
      "m_fWaitTime": 0,
      "m_CharStrID": "USER_ADMIN_NULL_NULL",
      "m_Talk_KOREA": "Âž\u000b9yÂť\u000b9tÂť\u000e9\u000180 Âžh\u000180Âž\u000e9\f8 Âž^j Âži\\Âžw\n8.",
      "m_fTalkTime": 0.03,
      "m_Talk_USA": "Âž\u000b9yÂť\u000b9tÂť\u000e9\u000180 Âžh\u000180Âž\u000e9\f8 Âž^j Âži\\Âžw\n8.",
      "m_Talk_JAPAN": "Âž\u000b9yÂť\u000b9tÂť\u000e9\u000180 Âžh\u000180Âž\u000e9\f8 Âž^j Âži\\Âžw\n8."
    },
    {
      "m_CutScenID": 10500001,
      "m_CutScenStrID": "LIFETIME_START_NKM_UNIT_C_FREEDOM_AKI",
      "m_bWaitClick": true,
      "m_fWaitTime": 0,
      "m_Face": "UNIT_SERIOUS",
      "m_CharStrID": "AKI_FREEDOM_NULL_NULL",
      "m_Pos": "C",
      "m_Talk_KOREA": "ÂžpZ Âžo\u000184ÂťujÂžk\n8 Âźl`ÂžXzÂťu\u000188 ÂžnZÂź\f9\u000180 Âžo\u000180 Âź\f9nÂťx\u000184 ÂźozÂžYoÂź\f9p Âžt\n8Âť\u000185ZÂś~\n8 ÂťdjÂžh\u000180 Âž\r8^Âž\u000b8\u000181Âť\u000b9^Âť\u000b9t!",
      "m_fTalkTime": 0.03,
      "m_Talk_USA": "ÂžpZ Âžo\u000184ÂťujÂžk\n8 Âźl`ÂžXzÂťu\u000188 ÂžnZÂź\f9\u000180 Âžo\u000180 Âź\f9nÂťx\u000184 ÂźozÂžYoÂź\f9p Âžt\n8Âť\u000185ZÂś~\n8 ÂťdjÂžh\u000180 Âž\r8^Âž\u000b8\u000181Âť\u000b9^Âť\u000b9t!",
      "m_Talk_JAPAN": "ÂžpZ Âžo\u000184ÂťujÂžk\n8 Âźl`ÂžXzÂťu\u000188 ÂžnZÂź\f9\u000180 Âžo\u000180 Âź\f9nÂťx\u000184 ÂźozÂžYoÂź\f9p Âžt\n8Âť\u000185ZÂś~\n8 ÂťdjÂžh\u000180 Âž\r8^Âž\u000b8\u000181Âť\u000b9^Âť\u000b9t!"
    },
    {
      "m_CutScenID": 10500001,
      "m_CutScenStrID": "LIFETIME_START_NKM_UNIT_C_FREEDOM_AKI",
      "m_bWaitClick": false,
      "m_fWaitTime": 0,
      "m_CharStrID": "AKI_FREEDOM_NULL_NULL",
      "m_Pos": "C_D"
    },
    {
      "m_CutScenID": 10500001,
      "m_CutScenStrID": "LIFETIME_START_NKM_UNIT_C_FREEDOM_AKI",
      "m_bWaitClick": true,
      "m_fWaitTime": 0,
      "m_CharStrID": "USER_ADMIN_NULL_NULL",
      "m_Talk_KOREA": "Âź\f9jÂź\f9j, Âś\u000183\u000184Âťp]Âť\u000b9tÂť\u000e9\u000180 Âť\u000b9tÂźh_Âžo\u000180Âś\u000181~. Âž\r8dÂťZtÂť\u000b8\f8 ÂžXzÂť\r8`Âžo\u000180 Âž\\\f8Âžw\n9Âź\f9\u000180ÂžZn Âžr\u000b9Âž\f9Z.",
      "m_fTalkTime": 0.03,
      "m_Talk_USA": "Âź\f9jÂź\f9j, Âś\u000183\u000184Âťp]Âť\u000b9tÂť\u000e9\u000180 Âť\u000b9tÂźh_Âžo\u000180Âś\u000181~. Âž\r8dÂťZtÂť\u000b8\f8 ÂžXzÂť\r8`Âžo\u000180 Âž\\\f8Âžw\n9Âź\f9\u000180ÂžZn Âžr\u000b9Âž\f9Z.",
      "m_Talk_JAPAN": "Âź\f9jÂź\f9j, Âś\u000183\u000184Âťp]Âť\u000b9tÂť\u000e9\u000180 Âť\u000b9tÂźh_Âžo\u000180Âś\u000181~. Âž\r8dÂťZtÂť\u000b8\f8 ÂžXzÂť\r8`Âžo\u000180 Âž\\\f8Âžw\n9Âź\f9\u000180ÂžZn Âžr\u000b9Âž\f9Z."
    },
    {
      "m_CutScenID": 10500001,
      "m_CutScenStrID": "LIFETIME_START_NKM_UNIT_C_FREEDOM_AKI",
      "m_bWaitClick": true,
      "m_fWaitTime": 0,
      "m_Face": "UNIT_HATE",
      "m_CharStrID": "AKI_FREEDOM_NULL_NULL",
      "m_Pos": "C",
      "m_Crash": 20,
      "m_Talk_KOREA": "Âžl~Âžn\u000188...... Âž\u000185jÂžXzÂź\f9\u000180......",
      "m_fTalkTime": 0.03,
      "m_Talk_USA": "Âžl~Âžn\u000188...... Âž\u000185jÂžXzÂź\f9\u000180......",
      "m_Talk_JAPAN": "Âžl~Âžn\u000188...... Âž\u000185jÂžXzÂź\f9\u000180......"
    },
    {
      "m_CutScenID": 10500001,
      "m_CutScenStrID": "LIFETIME_START_NKM_UNIT_C_FREEDOM_AKI",
      "m_bWaitClick": true,
      "m_fWaitTime": 0,
      "m_Face": "UNIT_DESPAIR",
      "m_CharStrID": "AKI_FREEDOM_NULL_NULL",
      "m_Pos": "C",
      "m_Crash": 10,
      "m_Talk_KOREA": "Âś\u000183\u000184Âž\u000185jÂťw` Âž\f9\r8Âžn\u000188Âťqn Âźc_ÂžYo Âžo\u000188Âź\f9jÂžw\n8 Âž\f9\u000b8Âś\u000f9p ÂźYÂž\r8dÂźYÂž\r8d Âť\\\n8 Âž^jÂťw` Âž\r8^Âť\u000b9tÂť\u000e9\u000180......",
      "m_fTalkTime": 0.03,
      "m_Talk_USA": "Âś\u000183\u000184Âž\u000185jÂťw` Âž\f9\r8Âžn\u000188Âťqn Âźc_ÂžYo Âžo\u000188Âź\f9jÂžw\n8 Âž\f9\u000b8Âś\u000f9p ÂźYÂž\r8dÂźYÂž\r8d Âť\\\n8 Âž^jÂťw` Âž\r8^Âť\u000b9tÂť\u000e9\u000180......",
      "m_Talk_JAPAN": "Âś\u000183\u000184Âž\u000185jÂťw` Âž\f9\r8Âžn\u000188Âťqn Âźc_ÂžYo Âžo\u000188Âź\f9jÂžw\n8 Âž\f9\u000b8Âś\u000f9p ÂźYÂž\r8dÂźYÂž\r8d Âť\\\n8 Âž^jÂťw` Âž\r8^Âť\u000b9tÂť\u000e9\u000180......"
    },
    {
      "m_CutScenID": 10500001,
      "m_CutScenStrID": "LIFETIME_START_NKM_UNIT_C_FREEDOM_AKI",
      "m_bWaitClick": true,
      "m_fWaitTime": 0,
      "m_Face": "UNIT_LAUGH",
      "m_CharStrID": "AKI_FREEDOM_NULL_NULL",
      "m_Pos": "C",
      "m_Crash": 40,
      "m_Talk_KOREA": "Âžoe! Âžo\u000180 Âžp\f9ÂťcZÂž\f9\u000188 Âžh\u000188Âťw^ÂťgpÂžw\n8!",
      "m_fTalkTime": 0.03,
      "m_Talk_USA": "Âžoe! Âžo\u000180 Âžp\f9ÂťcZÂž\f9\u000188 Âžh\u000188Âťw^ÂťgpÂžw\n8!",
      "m_Talk_JAPAN": "Âžoe! Âžo\u000180 Âžp\f9ÂťcZÂž\f9\u000188 Âžh\u000188Âťw^ÂťgpÂžw\n8!"
    }
  ],
  "root": [
    {
      "m_CutScenID": 10500001,
      "m_CutScenStrID": "LIFETIME_START_NKM_UNIT_C_FREEDOM_AKI",
      "m_bWaitClick": false,
      "m_fWaitTime": 0,
      "m_BGFileName": "BLACK",
      "m_bFadeIn": true,
      "m_fFadeTime": 1.5,
      "m_StartBGMFileName": "CUTSCENE_SILENCE"
    },
    {
      "m_CutScenID": 10500001,
      "m_CutScenStrID": "LIFETIME_START_NKM_UNIT_C_FREEDOM_AKI",
      "m_bWaitClick": false,
      "m_fWaitTime": 0.4,
      "m_fFlashBangTime": 0.25,
      "m_StartFXSoundName": "FX_CUTSCEN_KNOCK_WOOD"
    },
    {
      "m_CutScenID": 10500001,
      "m_CutScenStrID": "LIFETIME_START_NKM_UNIT_C_FREEDOM_AKI",
      "m_bWaitClick": false,
      "m_fWaitTime": 0.4,
      "m_fFlashBangTime": 0.25
    },
    {
      "m_CutScenID": 10500001,
      "m_CutScenStrID": "LIFETIME_START_NKM_UNIT_C_FREEDOM_AKI",
      "m_bWaitClick": false,
      "m_fWaitTime": 1.5,
      "m_fFlashBangTime": 0.25
    },
    {
      "m_CutScenID": 10500001,
      "m_CutScenStrID": "LIFETIME_START_NKM_UNIT_C_FREEDOM_AKI",
      "m_bWaitClick": true,
      "m_fWaitTime": 0,
      "m_Face": "UNIT_LAUGH",
      "m_CharStrID": "AKI_FREEDOM_NULL_NULL",
      "m_Pos": "C",
      "m_Crash": 30,
      "m_Talk_KOREA": "ÂžXzÂž\r8uÂť\u000b9j~ ÂžXz~ Âž\r8u~ Âť\u000b9j~",
      "m_fTalkTime": 0.03,
      "m_Talk_USA": "ÂžXzÂž\r8uÂť\u000b9j~ ÂžXz~ Âž\r8u~ Âť\u000b9j~",
      "m_Talk_JAPAN": "ÂžXzÂž\r8uÂť\u000b9j~ ÂžXz~ Âž\r8u~ Âť\u000b9j~"
    },
    {
      "m_CutScenID": 10500001,
      "m_CutScenStrID": "LIFETIME_START_NKM_UNIT_C_FREEDOM_AKI",
      "m_bWaitClick": true,
      "m_fWaitTime": 0,
      "m_Face": "UNIT_DESPAIR",
      "m_CharStrID": "AKI_FREEDOM_NULL_NULL",
      "m_Pos": "C",
      "m_Talk_KOREA": "Âžl~Âžn\u000188...... ÂžXzÂť\r8`ÂžoZ Âť\u000182^Âť\r9z Âť\\gÂś\u000f9p Âžh\u000180Âť\f8\f8 Âś~\n8Âž\u000b9p Âś~Âť\r8`, ÂžwZÂžwn......",
      "m_fTalkTime": 0.03,
      "m_Talk_USA": "Âžl~Âžn\u000188...... ÂžXzÂť\r8`ÂžoZ Âť\u000182^Âť\r9z Âť\\gÂś\u000f9p Âžh\u000180Âť\f8\f8 Âś~\n8Âž\u000b9p Âś~Âť\r8`, ÂžwZÂžwn......",
      "m_Talk_JAPAN": "Âžl~Âžn\u000188...... ÂžXzÂť\r8`ÂžoZ Âť\u000182^Âť\r9z Âť\\gÂś\u000f9p Âžh\u000180Âť\f8\f8 Âś~\n8Âž\u000b9p Âś~Âť\r8`, ÂžwZÂžwn......"
    },
    {
      "m_CutScenID": 10500001,
      "m_CutScenStrID": "LIFETIME_START_NKM_UNIT_C_FREEDOM_AKI",
      "m_bWaitClick": true,
      "m_fWaitTime": 0,
      "m_Face": "UNIT_SURPRISE",
      "m_CharStrID": "AKI_FREEDOM_NULL_NULL",
      "m_Pos": "C",
      "m_Talk_KOREA": "Âž\f9i, Âťz\u000184Âžo\u000180 Âži\u000180Âťpt Âž\r8^Âži^ÂťZt?",
      "m_fTalkTime": 0.03,
      "m_Talk_USA": "Âž\f9i, Âťz\u000184Âžo\u000180 Âži\u000180Âťpt Âž\r8^Âži^ÂťZt?",
      "m_Talk_JAPAN": "Âž\f9i, Âťz\u000184Âžo\u000180 Âži\u000180Âťpt Âž\r8^Âži^ÂťZt?"
    },
    {
      "m_CutScenID": 10500001,
      "m_CutScenStrID": "LIFETIME_START_NKM_UNIT_C_FREEDOM_AKI",
      "m_bWaitClick": true,
      "m_fWaitTime": 0,
      "m_Face": "UNIT_PRIDE",
      "m_CharStrID": "AKI_FREEDOM_NULL_NULL",
      "m_Pos": "C",
      "m_Talk_KOREA": "Âžp\f9Âťwd, Âť\\aÂť\f9qÂžo\u000180Âť\u000b8\f8 Âž\r8j Âž\u000185jÂž\u000b9nÂť\u000e9\u000180ÂžZn Âžo\u000180Âť\r9~ Âś\u000181zÂžZoÂžo\n8 Âźi^Âž^pÂź\f9jÂť\u000b9tÂť\u000b9^Âś\u000185`Âžl\f8.",
      "m_fTalkTime": 0.03,
      "m_Talk_USA": "Âžp\f9Âťwd, Âť\\aÂť\f9qÂžo\u000180Âť\u000b8\f8 Âž\r8j Âž\u000185jÂž\u000b9nÂť\u000e9\u000180ÂžZn Âžo\u000180Âť\r9~ Âś\u000181zÂžZoÂžo\n8 Âźi^Âž^pÂź\f9jÂť\u000b9tÂť\u000b9^Âś\u000185`Âžl\f8.",
      "m_Talk_JAPAN": "Âžp\f9Âťwd, Âť\\aÂť\f9qÂžo\u000180Âť\u000b8\f8 Âž\r8j Âž\u000185jÂž\u000b9nÂť\u000e9\u000180ÂžZn Âžo\u000180Âť\r9~ Âś\u000181zÂžZoÂžo\n8 Âźi^Âž^pÂź\f9jÂť\u000b9tÂť\u000b9^Âś\u000185`Âžl\f8."
    },
    {
      "m_CutScenID": 10500001,
      "m_CutScenStrID": "LIFETIME_START_NKM_UNIT_C_FREEDOM_AKI",
      "m_bWaitClick": true,
      "m_fWaitTime": 0,
      "m_CharStrID": "AKI_FREEDOM_NULL_NULL",
      "m_Pos": "C",
      "m_Talk_KOREA": "Âžo\u000180Âť\f8~ Âť\u000f9\u000180Âť\u000e9\u000180 Âť\f8~Âť\n9\f8Âź\f9jÂś\u000f8` Âź\f9nÂťw^Âť\f8\f8 Âź\f9\u000180 ÂťgnÂťptÂž\f9\u000188Âś\u000f8pÂžh\u000180Âžl\f8.",
      "m_fTalkTime": 0.03,
      "m_Talk_USA": "Âžo\u000180Âť\f8~ Âť\u000f9\u000180Âť\u000e9\u000180 Âť\f8~Âť\n9\f8Âź\f9jÂś\u000f8` Âź\f9nÂťw^Âť\f8\f8 Âź\f9\u000180 ÂťgnÂťptÂž\f9\u000188Âś\u000f8pÂžh\u000180Âžl\f8.",
      "m_Talk_JAPAN": "Âžo\u000180Âť\f8~ Âť\u000f9\u000180Âť\u000e9\u000180 Âť\f8~Âť\n9\f8Âź\f9jÂś\u000f8` Âź\f9nÂťw^Âť\f8\f8 Âź\f9\u000180 ÂťgnÂťptÂž\f9\u000188Âś\u000f8pÂžh\u000180Âžl\f8."
    },
    {
      "m_CutScenID": 10500001,
      "m_CutScenStrID": "LIFETIME_START_NKM_UNIT_C_FREEDOM_AKI",
      "m_bWaitClick": true,
      "m_fWaitTime": 0,
      "m_Face": "UNIT_HATE",
      "m_CharStrID": "AKI_FREEDOM_NULL_NULL",
      "m_Pos": "C",
      "m_Talk_KOREA": "......Âž\f9ZÂť\u000b9^, Âž\r8pÂś\u000185d.",
      "m_fTalkTime": 0.03,
      "m_Talk_USA": "......Âž\f9ZÂť\u000b9^, Âž\r8pÂś\u000185d.",
      "m_Talk_JAPAN": "......Âž\f9ZÂť\u000b9^, Âž\r8pÂś\u000185d."
    },
    {
      "m_CutScenID": 10500001,
      "m_CutScenStrID": "LIFETIME_START_NKM_UNIT_C_FREEDOM_AKI",
      "m_bWaitClick": true,
      "m_fWaitTime": 0,
      "m_CharStrID": "AKI_FREEDOM_NULL_NULL",
      "m_Pos": "C",
      "m_Talk_KOREA": "ÂžYoÂś~\n9Âź\f9\u000180 Âť\u000f9\u000180Âť\u000b9^ Âžo\u000180Âś~ Âť\\gÂž\u000f9dÂžZp Âž\f9^ Âťdp Âś\u000184~Âźl`Âž\r8hÂž\f9ZÂžl\f8?",
      "m_fTalkTime": 0.03,
      "m_Talk_USA": "ÂžYoÂś~\n9Âź\f9\u000180 Âť\u000f9\u000180Âť\u000b9^ Âžo\u000180Âś~ Âť\\gÂž\u000f9dÂžZp Âž\f9^ Âťdp Âś\u000184~Âźl`Âž\r8hÂž\f9ZÂžl\f8?",
      "m_Talk_JAPAN": "ÂžYoÂś~\n9Âź\f9\u000180 Âť\u000f9\u000180Âť\u000b9^ Âžo\u000180Âś~ Âť\\gÂž\u000f9dÂžZp Âž\f9^ Âťdp Âś\u000184~Âźl`Âž\r8hÂž\f9ZÂžl\f8?"
    },
    {
      "m_CutScenID": 10500001,
      "m_CutScenStrID": "LIFETIME_START_NKM_UNIT_C_FREEDOM_AKI",
      "m_bWaitClick": true,
      "m_fWaitTime": 0,
      "m_Face": "UNIT_LAUGH",
      "m_CharStrID": "AKI_FREEDOM_NULL_NULL",
      "m_Pos": "C",
      "m_Crash": 40,
      "m_Talk_KOREA": "ÂžXzÂž\r8uÂť\u000b9j ÂžweÂťz\u000180Âž\u000b9t Âžp\f9ÂťcZÂť\u000e9\u000180 Âť\u000182ZÂťx[ Âťc^ Âť\u000f8ZÂť\u000b8\f8 Âť\u000185ZÂť\u000f8\f9 Âś~kÂžo\n8 Âś\u000f8` Âž\r8\f8Âťn\u000e9 Âž^\u000e8Âś\u000f8\u000e8Âžp\u000184 Âž\r8^ÂžoZ Âś~ÂžidÂžl\f8!",
      "m_fTalkTime": 0.03,
      "m_Talk_USA": "ÂžXzÂž\r8uÂť\u000b9j ÂžweÂťz\u000180Âž\u000b9t Âžp\f9ÂťcZÂť\u000e9\u000180 Âť\u000182ZÂťx[ Âťc^ Âť\u000f8ZÂť\u000b8\f8 Âť\u000185ZÂť\u000f8\f9 Âś~kÂžo\n8 Âś\u000f8` Âž\r8\f8Âťn\u000e9 Âž^\u000e8Âś\u000f8\u000e8Âžp\u000184 Âž\r8^ÂžoZ Âś~ÂžidÂžl\f8!",
      "m_Talk_JAPAN": "ÂžXzÂž\r8uÂť\u000b9j ÂžweÂťz\u000180Âž\u000b9t Âžp\f9ÂťcZÂť\u000e9\u000180 Âť\u000182ZÂťx[ Âťc^ Âť\u000f8ZÂť\u000b8\f8 Âť\u000185ZÂť\u000f8\f9 Âś~kÂžo\n8 Âś\u000f8` Âž\r8\f8Âťn\u000e9 Âž^\u000e8Âś\u000f8\u000e8Âžp\u000184 Âž\r8^ÂžoZ Âś~ÂžidÂžl\f8!"
    },
    {
      "m_CutScenID": 10500001,
      "m_CutScenStrID": "LIFETIME_START_NKM_UNIT_C_FREEDOM_AKI",
      "m_bWaitClick": false,
      "m_fWaitTime": 0,
      "m_bFadeIn": false,
      "m_fFadeTime": 2
    },
    {
      "m_CutScenID": 10500001,
      "m_CutScenStrID": "LIFETIME_START_NKM_UNIT_C_FREEDOM_AKI",
      "m_bWaitClick": false,
      "m_fWaitTime": 0,
      "m_BGFileName": "LIFETIME",
      "m_Face": "UNIT_LAUGH",
      "m_bFadeIn": true,
      "m_fFadeTime": 3,
      "m_StartFXSoundName": "FX_CUTSCEN_DOOR_WOOD",
      "m_CharStrID": "AKI_FREEDOM_NULL_NULL",
      "m_Pos": "C_D"
    },
    {
      "m_CutScenID": 10500001,
      "m_CutScenStrID": "LIFETIME_START_NKM_UNIT_C_FREEDOM_AKI",
      "m_bWaitClick": true,
      "m_fWaitTime": 0,
      "m_StartBGMFileName": "CUTSCENE_HOPE",
      "m_CharStrID": "USER_ADMIN_NULL_NULL",
      "m_Talk_KOREA": "Âť~jÂś~eÂťZt, Âž\f9ZÂźXt Âžhe.",
      "m_fTalkTime": 0.03,
      "m_Talk_USA": "Âť~jÂś~eÂťZt, Âž\f9ZÂźXt Âžhe.",
      "m_Talk_JAPAN": "Âť~jÂś~eÂťZt, Âž\f9ZÂźXt Âžhe."
    },
    {
      "m_CutScenID": 10500001,
      "m_CutScenStrID": "LIFETIME_START_NKM_UNIT_C_FREEDOM_AKI",
      "m_bWaitClick": true,
      "m_fWaitTime": 0,
      "m_Face": "UNIT_SURPRISE",
      "m_CharStrID": "AKI_FREEDOM_NULL_NULL",
      "m_Pos": "C",
      "m_Crash": 100,
      "m_Talk_KOREA": "ÂžiZÂťw^ÂžhcÂś\u000185nÂžwoÂžo\u000180Âž\f9\u000189!",
      "m_fTalkTime": 0.03,
      "m_Talk_USA": "ÂžiZÂťw^ÂžhcÂś\u000185nÂžwoÂžo\u000180Âž\f9\u000189!",
      "m_Talk_JAPAN": "ÂžiZÂťw^ÂžhcÂś\u000185nÂžwoÂžo\u000180Âž\f9\u000189!"
    },
    {
      "m_CutScenID": 10500001,
      "m_CutScenStrID": "LIFETIME_START_NKM_UNIT_C_FREEDOM_AKI",
      "m_bWaitClick": true,
      "m_fWaitTime": 0,
      "m_CharStrID": "AKI_FREEDOM_NULL_NULL",
      "m_Pos": "C",
      "m_Crash": 20,
      "m_Talk_KOREA": "Âť^ZÂť^ZÂť^ZÂť^ZÂś\u000181zÂžZ\u000184Âžl\f8? ÂžizÂś\u000184~ Âť{dÂź\f9jÂť\r9z ÂťgtÂžh\u000180Âžk\f8Âžh\u000180Âžl\f8? Âźj\u000185Âž\u000b9n......!",
      "m_fTalkTime": 0.09,
      "m_Talk_USA": "Âť^ZÂť^ZÂť^ZÂť^ZÂś\u000181zÂžZ\u000184Âžl\f8? ÂžizÂś\u000184~ Âť{dÂź\f9jÂť\r9z ÂťgtÂžh\u000180Âžk\f8Âžh\u000180Âžl\f8? Âźj\u000185Âž\u000b9n......!",
      "m_Talk_JAPAN": "Âť^ZÂť^ZÂť^ZÂť^ZÂś\u000181zÂžZ\u000184Âžl\f8? ÂžizÂś\u000184~ Âť{dÂź\f9jÂť\r9z ÂťgtÂžh\u000180Âžk\f8Âžh\u000180Âžl\f8? Âźj\u000185Âž\u000b9n......!"
    },
    {
      "m_CutScenID": 10500001,
      "m_CutScenStrID": "LIFETIME_START_NKM_UNIT_C_FREEDOM_AKI",
      "m_bWaitClick": true,
      "m_fWaitTime": 0,
      "m_Face": "UNIT_SERIOUS",
      "m_CharStrID": "AKI_FREEDOM_NULL_NULL",
      "m_Pos": "C",
      "m_Crash": 50,
      "m_Talk_KOREA": "Âť\u000b9\u000185Âž\u000b9pÂťcZ ÂžXzÂž\r8uÂť\u000b9jÂžoj Âť\u000182^ÂťqnÂž\\`Âťgo Âť\u000185ZÂť\u000f8\f9ÂžoZ Âť[\u000184ÂťvzÂś\u000f9p?!",
      "m_fTalkTime": 0.09,
      "m_Talk_USA": "Âť\u000b9\u000185Âž\u000b9pÂťcZ ÂžXzÂž\r8uÂť\u000b9jÂžoj Âť\u000182^ÂťqnÂž\\`Âťgo Âť\u000185ZÂť\u000f8\f9ÂžoZ Âť[\u000184ÂťvzÂś\u000f9p?!",
      "m_Talk_JAPAN": "Âť\u000b9\u000185Âž\u000b9pÂťcZ ÂžXzÂž\r8uÂť\u000b9jÂžoj Âť\u000182^ÂťqnÂž\\`Âťgo Âť\u000185ZÂť\u000f8\f9ÂžoZ Âť[\u000184ÂťvzÂś\u000f9p?!"
    },
    {
      "m_CutScenID": 10500001,
      "m_CutScenStrID": "LIFETIME_START_NKM_UNIT_C_FREEDOM_AKI",
      "m_bWaitClick": false,
      "m_fWaitTime": 0,
      "m_CharStrID": "AKI_FREEDOM_NULL_NULL",
      "m_Pos": "C_D"
    },
    {
      "m_CutScenID": 10500001,
      "m_CutScenStrID": "LIFETIME_START_NKM_UNIT_C_FREEDOM_AKI",
      "m_bWaitClick": true,
      "m_fWaitTime": 0,
      "m_CharStrID": "USER_ADMIN_NULL_NULL",
      "m_Talk_KOREA": "......Âś\u000183\u000184Âť\r9~ Âźb\u000184ÂťvzÂź\f9n Âť\u000185ZÂť\u000f8\f9 Âś~kÂžo\n8 Âś\u000180 Âži\\ÂžoZ Âť\u000191dÂťa\f8Âť\r9z, Âž\r8^Âžh\u000180ÂťcZ Âžo\u000180Âť\r9~ ÂžnZÂźijÂź\f9n Âś\u000f9\u000f9Âži\f8 Âž\f9^ Âť\u000f9\u000180Âś\u000180\n8Âź\f9\u000180.",
      "m_fTalkTime": 0.03,
      "m_Talk_USA": "......Âś\u000183\u000184Âť\r9~ Âźb\u000184ÂťvzÂź\f9n Âť\u000185ZÂť\u000f8\f9 Âś~kÂžo\n8 Âś\u000180 Âži\\ÂžoZ Âť\u000191dÂťa\f8Âť\r9z, Âž\r8^Âžh\u000180ÂťcZ Âžo\u000180Âť\r9~ ÂžnZÂźijÂź\f9n Âś\u000f9\u000f9Âži\f8 Âž\f9^ Âť\u000f9\u000180Âś\u000180\n8Âź\f9\u000180.",
      "m_Talk_JAPAN": "......Âś\u000183\u000184Âť\r9~ Âźb\u000184ÂťvzÂź\f9n Âť\u000185ZÂť\u000f8\f9 Âś~kÂžo\n8 Âś\u000180 Âži\\ÂžoZ Âť\u000191dÂťa\f8Âť\r9z, Âž\r8^Âžh\u000180ÂťcZ Âžo\u000180Âť\r9~ ÂžnZÂźijÂź\f9n Âś\u000f9\u000f9Âži\f8 Âž\f9^ Âť\u000f9\u000180Âś\u000180\n8Âź\f9\u000180."
    },
    {
      "m_CutScenID": 10500001,
      "m_CutScenStrID": "LIFETIME_START_NKM_UNIT_C_FREEDOM_AKI",
      "m_bWaitClick": true,
      "m_fWaitTime": 0,
      "m_CharStrID": "AKI_FREEDOM_NULL_NULL",
      "m_Pos": "C",
      "m_Crash": 30,
      "m_Talk_KOREA": "ÂžXzÂž\r8uÂť\u000b9jÂžo\u000180 Âžp\n8Âťu\u000188 Âž\\aÂžj\n8Âť\u000b9tÂś\u000f9pÂžl\f8? Âś\u000183\u000184Âť\r9\u000180 Âťvz Âži\\Âžh\u000180Âžl\f8!",
      "m_fTalkTime": 0.03,
      "m_Talk_USA": "ÂžXzÂž\r8uÂť\u000b9jÂžo\u000180 Âžp\n8Âťu\u000188 Âž\\aÂžj\n8Âť\u000b9tÂś\u000f9pÂžl\f8? Âś\u000183\u000184Âť\r9\u000180 Âťvz Âži\\Âžh\u000180Âžl\f8!",
      "m_Talk_JAPAN": "ÂžXzÂž\r8uÂť\u000b9jÂžo\u000180 Âžp\n8Âťu\u000188 Âž\\aÂžj\n8Âť\u000b9tÂś\u000f9pÂžl\f8? Âś\u000183\u000184Âť\r9\u000180 Âťvz Âži\\Âžh\u000180Âžl\f8!"
    },
    {
      "m_CutScenID": 10500001,
      "m_CutScenStrID": "LIFETIME_START_NKM_UNIT_C_FREEDOM_AKI",
      "m_bWaitClick": true,
      "m_fWaitTime": 0,
      "m_CharStrID": "AKI_FREEDOM_NULL_NULL",
      "m_Pos": "C",
      "m_Talk_KOREA": "Âť\u000182ZÂťx[ Âžo\u000180 Âť~\u000e9 Âžh\u000180Âť\f8jÂś~\n8Âžid Âžp\n8Âź\f9nÂź[` ÂžtZ Âž~\u000e8Âťx[Âś\u000f9ZÂžr` ÂťvzÂž\u000b8tÂź\u000b8\u000184 Âś~kÂžo\n8 Âś\u000184 Âž^\u000e8Âś\u000f8\u000e8 ÂťedÂž[\u000e8ÂžoZ Âś~Âťo\u000188Âś\u000f9pÂžl\f8!",
      "m_fTalkTime": 0.03,
      "m_Talk_USA": "Âť\u000182ZÂťx[ Âžo\u000180 Âť~\u000e9 Âžh\u000180Âť\f8jÂś~\n8Âžid Âžp\n8Âź\f9nÂź[` ÂžtZ Âž~\u000e8Âťx[Âś\u000f9ZÂžr` ÂťvzÂž\u000b8tÂź\u000b8\u000184 Âś~kÂžo\n8 Âś\u000184 Âž^\u000e8Âś\u000f8\u000e8 ÂťedÂž[\u000e8ÂžoZ Âś~Âťo\u000188Âś\u000f9pÂžl\f8!",
      "m_Talk_JAPAN": "Âť\u000182ZÂťx[ Âžo\u000180 Âť~\u000e9 Âžh\u000180Âť\f8jÂś~\n8Âžid Âžp\n8Âź\f9nÂź[` ÂžtZ Âž~\u000e8Âťx[Âś\u000f9ZÂžr` ÂťvzÂž\u000b8tÂź\u000b8\u000184 Âś~kÂžo\n8 Âś\u000184 Âž^\u000e8Âś\u000f8\u000e8 ÂťedÂž[\u000e8ÂžoZ Âś~Âťo\u000188Âś\u000f9pÂžl\f8!"
    },
    {
      "m_CutScenID": 10500001,
      "m_CutScenStrID": "LIFETIME_START_NKM_UNIT_C_FREEDOM_AKI",
      "m_bWaitClick": false,
      "m_fWaitTime": 0,
      "m_CharStrID": "AKI_FREEDOM_NULL_NULL",
      "m_Pos": "C_D"
    },
    {
      "m_CutScenID": 10500001,
      "m_CutScenStrID": "LIFETIME_START_NKM_UNIT_C_FREEDOM_AKI",
      "m_bWaitClick": true,
      "m_fWaitTime": 0,
      "m_CharStrID": "USER_ADMIN_NULL_NULL",
      "m_Talk_KOREA": "ÂťZ^Âťz\u000180 Âžo\u000188Âť~\u000e9Âžp\n9Âžo\u000184 Âž~\u000e9Âś~\n9Âžo\u000180Âťo\u000188 Âžh\u000180Âť\f8\f8ÂžZnÂť\u000182\n8ÂźZ~ Âžp\f9Âžp\f9Âź\f9\u000180 ÂžtjÂž\f9\u000188 Âź\f9pÂžw\n8 Âś~dÂžo\u000180 Âž\f9^ Âž\r8qÂź\r8^ÂťZtÂťw`......",
      "m_fTalkTime": 0.03,
      "m_Talk_USA": "ÂťZ^Âťz\u000180 Âžo\u000188Âť~\u000e9Âžp\n9Âžo\u000184 Âž~\u000e9Âś~\n9Âžo\u000180Âťo\u000188 Âžh\u000180Âť\f8\f8ÂžZnÂť\u000182\n8ÂźZ~ Âžp\f9Âžp\f9Âź\f9\u000180 ÂžtjÂž\f9\u000188 Âź\f9pÂžw\n8 Âś~dÂžo\u000180 Âž\f9^ Âž\r8qÂź\r8^ÂťZtÂťw`......",
      "m_Talk_JAPAN": "ÂťZ^Âťz\u000180 Âžo\u000188Âť~\u000e9Âžp\n9Âžo\u000184 Âž~\u000e9Âś~\n9Âžo\u000180Âťo\u000188 Âžh\u000180Âť\f8\f8ÂžZnÂť\u000182\n8ÂźZ~ Âžp\f9Âžp\f9Âź\f9\u000180 ÂžtjÂž\f9\u000188 Âź\f9pÂžw\n8 Âś~dÂžo\u000180 Âž\f9^ Âž\r8qÂź\r8^ÂťZtÂťw`......"
    },
    {
      "m_CutScenID": 10500001,
      "m_CutScenStrID": "LIFETIME_START_NKM_UNIT_C_FREEDOM_AKI",
      "m_bWaitClick": true,
      "m_fWaitTime": 0,
      "m_CharStrID": "USER_ADMIN_NULL_NULL",
      "m_Talk_KOREA": "Âžl~ÂžZp ÂťX\u000180Âś~\n8 Âž\r8dÂťZt ÂžXzÂž\r8uÂť\u000b9jÂžo\u000188ÂžZ\u000184.",
      "m_fTalkTime": 0.03,
      "m_Talk_USA": "Âžl~ÂžZp ÂťX\u000180Âś~\n8 Âž\r8dÂťZt ÂžXzÂž\r8uÂť\u000b9jÂžo\u000188ÂžZ\u000184.",
      "m_Talk_JAPAN": "Âžl~ÂžZp ÂťX\u000180Âś~\n8 Âž\r8dÂťZt ÂžXzÂž\r8uÂť\u000b9jÂžo\u000188ÂžZ\u000184."
    },
    {
      "m_CutScenID": 10500001,
      "m_CutScenStrID": "LIFETIME_START_NKM_UNIT_C_FREEDOM_AKI",
      "m_bWaitClick": true,
      "m_fWaitTime": 0,
      "m_Face": "UNIT_SURPRISE",
      "m_CharStrID": "AKI_FREEDOM_NULL_NULL",
      "m_Pos": "C",
      "m_Talk_KOREA": "......Âžp\n8Âźoz ÂžXzÂž\r8uÂť\u000b9j Âž\f9\u000188Âť~jÂťcZÂžs\u000188Âź\f9jÂž[\u000e8Âžh\u000180Âžl\f8?",
      "m_fTalkTime": 0.03,
      "m_Talk_USA": "......Âžp\n8Âźoz ÂžXzÂž\r8uÂť\u000b9j Âž\f9\u000188Âť~jÂťcZÂžs\u000188Âź\f9jÂž[\u000e8Âžh\u000180Âžl\f8?",
      "m_Talk_JAPAN": "......Âžp\n8Âźoz ÂžXzÂž\r8uÂť\u000b9j Âž\f9\u000188Âť~jÂťcZÂžs\u000188Âź\f9jÂž[\u000e8Âžh\u000180Âžl\f8?"
    },
    {
      "m_CutScenID": 10500001,
      "m_CutScenStrID": "LIFETIME_START_NKM_UNIT_C_FREEDOM_AKI",
      "m_bWaitClick": false,
      "m_fWaitTime": 0,
      "m_bFadeIn": false,
      "m_fFadeTime": 1
    },
    {
      "m_CutScenID": 10500001,
      "m_CutScenStrID": "LIFETIME_START_NKM_UNIT_C_FREEDOM_AKI",
      "m_bWaitClick": false,
      "m_fWaitTime": 0,
      "m_BGFileName": "LIFETIME",
      "m_bFadeIn": true,
      "m_fFadeTime": 1
    },
    {
      "m_CutScenID": 10500001,
      "m_CutScenStrID": "LIFETIME_START_NKM_UNIT_C_FREEDOM_AKI",
      "m_bWaitClick": true,
      "m_fWaitTime": 0,
      "m_Face": "UNIT_LAUGH",
      "m_CharStrID": "AKI_FREEDOM_NULL_NULL",
      "m_Pos": "C",
      "m_Talk_KOREA": "Âž\f9Z, Âž\f9ZÂź\f9j, Âž\f9ZÂź\f9jÂź\f9j...... Âś\u000183\u000184Âť\r9zÂť\u000b9^Âś\u000185` Âžp\f9Âž\u000f8\u000180Âś~\n8 Âž\f9`ÂťptÂžw\n8Âť\u000e9\u000180 Âś\u000f9tÂť\r8\n8Âź\f9jÂť\u000b9^Âś\u000185` Âž^\u000e8Âś\u000184~Âž\u000b9nÂťptÂś\u000f9p......",
      "m_fTalkTime": 0.03,
      "m_Talk_USA": "Âž\f9Z, Âž\f9ZÂź\f9j, Âž\f9ZÂź\f9jÂź\f9j...... Âś\u000183\u000184Âť\r9zÂť\u000b9^Âś\u000185` Âžp\f9Âž\u000f8\u000180Âś~\n8 Âž\f9`ÂťptÂžw\n8Âť\u000e9\u000180 Âś\u000f9tÂť\r8\n8Âź\f9jÂť\u000b9^Âś\u000185` Âž^\u000e8Âś\u000184~Âž\u000b9nÂťptÂś\u000f9p......",
      "m_Talk_JAPAN": "Âž\f9Z, Âž\f9ZÂź\f9j, Âž\f9ZÂź\f9jÂź\f9j...... Âś\u000183\u000184Âť\r9zÂť\u000b9^Âś\u000185` Âžp\f9Âž\u000f8\u000180Âś~\n8 Âž\f9`ÂťptÂžw\n8Âť\u000e9\u000180 Âś\u000f9tÂť\r8\n8Âź\f9jÂť\u000b9^Âś\u000185` Âž^\u000e8Âś\u000184~Âž\u000b9nÂťptÂś\u000f9p......"
    },
    {
      "m_CutScenID": 10500001,
      "m_CutScenStrID": "LIFETIME_START_NKM_UNIT_C_FREEDOM_AKI",
      "m_bWaitClick": true,
      "m_fWaitTime": 0,
      "m_CharStrID": "AKI_FREEDOM_NULL_NULL",
      "m_Pos": "C",
      "m_Crash": 15,
      "m_Talk_KOREA": "ÂžwZÂžv_ ÂťwdÂž\f8\n8Âź\f9jÂž\u000b9nÂžw\n8 Âś\u000183\u000184Âť\r8zÂžh\u000180Âžl\f8. Âž\f9ZÂś\u000185` Âžpn Âťwd Âť\u000b9t Âť\\aÂť\u000b9\u000180Âžo\u000184 Âś~ Âž\f9ZÂž\u000b9nÂžsp? ÂťZtÂžid?",
      "m_fTalkTime": 0.03,
      "m_Talk_USA": "ÂžwZÂžv_ ÂťwdÂž\f8\n8Âź\f9jÂž\u000b9nÂžw\n8 Âś\u000183\u000184Âť\r8zÂžh\u000180Âžl\f8. Âž\f9ZÂś\u000185` Âžpn Âťwd Âť\u000b9t Âť\\aÂť\u000b9\u000180Âžo\u000184 Âś~ Âž\f9ZÂž\u000b9nÂžsp? ÂťZtÂžid?",
      "m_Talk_JAPAN": "ÂžwZÂžv_ ÂťwdÂž\f8\n8Âź\f9jÂž\u000b9nÂžw\n8 Âś\u000183\u000184Âť\r8zÂžh\u000180Âžl\f8. Âž\f9ZÂś\u000185` Âžpn Âťwd Âť\u000b9t Âť\\aÂť\u000b9\u000180Âžo\u000184 Âś~ Âž\f9ZÂž\u000b9nÂžsp? ÂťZtÂžid?"
    },
    {
      "m_CutScenID": 10500001,
      "m_CutScenStrID": "LIFETIME_START_NKM_UNIT_C_FREEDOM_AKI",
      "m_bWaitClick": false,
      "m_fWaitTime": 0,
      "m_CharStrID": "AKI_FREEDOM_NULL_NULL",
      "m_Pos": "C_D"
    },
    {
      "m_CutScenID": 10500001,
      "m_CutScenStrID": "LIFETIME_START_NKM_UNIT_C_FREEDOM_AKI",
      "m_bWaitClick": true,
      "m_fWaitTime": 0,
      "m_CharStrID": "USER_ADMIN_NULL_NULL",
      "m_Talk_KOREA": "ÂťedÂťwdÂź\f9p Âś\u000f8Y Âži\\Âžo\u000180 ÂžwZÂť\u000b9\u000180Âžn\u000188Âťqn ÂťgtÂťp\u000184ÂťZt.",
      "m_fTalkTime": 0.03,
      "m_Talk_USA": "ÂťedÂťwdÂź\f9p Âś\u000f8Y Âži\\Âžo\u000180 ÂžwZÂť\u000b9\u000180Âžn\u000188Âťqn ÂťgtÂťp\u000184ÂťZt.",
      "m_Talk_JAPAN": "ÂťedÂťwdÂź\f9p Âś\u000f8Y Âži\\Âžo\u000180 ÂžwZÂť\u000b9\u000180Âžn\u000188Âťqn ÂťgtÂťp\u000184ÂťZt."
    },
    {
      "m_CutScenID": 10500001,
      "m_CutScenStrID": "LIFETIME_START_NKM_UNIT_C_FREEDOM_AKI",
      "m_bWaitClick": true,
      "m_fWaitTime": 0,
      "m_Face": "UNIT_HATE",
      "m_CharStrID": "AKI_FREEDOM_NULL_NULL",
      "m_Pos": "C",
      "m_Crash": 40,
      "m_Talk_KOREA": "Âž\u000f8\u000180Âžis......",
      "m_fTalkTime": 0.03,
      "m_Talk_USA": "Âž\u000f8\u000180Âžis......",
      "m_Talk_JAPAN": "Âž\u000f8\u000180Âžis......"
    },
    {
      "m_CutScenID": 10500001,
      "m_CutScenStrID": "LIFETIME_START_NKM_UNIT_C_FREEDOM_AKI",
      "m_bWaitClick": false,
      "m_fWaitTime": 0,
      "m_CharStrID": "AKI_FREEDOM_NULL_NULL",
      "m_Pos": "C_D"
    },
    {
      "m_CutScenID": 10500001,
      "m_CutScenStrID": "LIFETIME_START_NKM_UNIT_C_FREEDOM_AKI",
      "m_bWaitClick": true,
      "m_fWaitTime": 0,
      "m_CharStrID": "USER_ADMIN_NULL_NULL",
      "m_Talk_KOREA": "Âťz\u000188Âťqp Âś\u000183\u000184Âťp]Âť\u000b9tÂś\u000f9p Âž\r8dÂťZtÂžidÂś\u000f8` Âť\u000182^Âžo\u000180Âžo\u000181ÂžoZ Âžt\n8Âť\u000b9tÂś~ÂťXj Âź\f9p ÂžYoÂś~\n9Âžo\n8 Âži\\Âť\u000b9tÂťZt.",
      "m_fTalkTime": 0.03,
      "m_Talk_USA": "Âťz\u000188Âťqp Âś\u000183\u000184Âťp]Âť\u000b9tÂś\u000f9p Âž\r8dÂťZtÂžidÂś\u000f8` Âť\u000182^Âžo\u000180Âžo\u000181ÂžoZ Âžt\n8Âť\u000b9tÂś~ÂťXj Âź\f9p ÂžYoÂś~\n9Âžo\n8 Âži\\Âť\u000b9tÂťZt.",
      "m_Talk_JAPAN": "Âťz\u000188Âťqp Âś\u000183\u000184Âťp]Âť\u000b9tÂś\u000f9p Âž\r8dÂťZtÂžidÂś\u000f8` Âť\u000182^Âžo\u000180Âžo\u000181ÂžoZ Âžt\n8Âť\u000b9tÂś~ÂťXj Âź\f9p ÂžYoÂś~\n9Âžo\n8 Âži\\Âť\u000b9tÂťZt."
    },
    {
      "m_CutScenID": 10500001,
      "m_CutScenStrID": "LIFETIME_START_NKM_UNIT_C_FREEDOM_AKI",
      "m_bWaitClick": true,
      "m_fWaitTime": 0,
      "m_CharStrID": "USER_ADMIN_NULL_NULL",
      "m_Talk_KOREA": "Âžw\n9ÂžmdÂžo\u000180 ÂźoeÂž\u000b9z Âžr\n8 Âźf^ÂžoZ Âž^j Âž\r8^Âžw\n8, Âž\f9^ Âś\u000183\u000184Âť\r9zÂťXj? Âź\f9jÂź\f9jÂź\f9j.",
      "m_fTalkTime": 0.03,
      "m_Talk_USA": "Âžw\n9ÂžmdÂžo\u000180 ÂźoeÂž\u000b9z Âžr\n8 Âźf^ÂžoZ Âž^j Âž\r8^Âžw\n8, Âž\f9^ Âś\u000183\u000184Âť\r9zÂťXj? Âź\f9jÂź\f9jÂź\f9j.",
      "m_Talk_JAPAN": "Âžw\n9ÂžmdÂžo\u000180 ÂźoeÂž\u000b9z Âžr\n8 Âźf^ÂžoZ Âž^j Âž\r8^Âžw\n8, Âž\f9^ Âś\u000183\u000184Âť\r9zÂťXj? Âź\f9jÂź\f9jÂź\f9j."
    },
    {
      "m_CutScenID": 10500001,
      "m_CutScenStrID": "LIFETIME_START_NKM_UNIT_C_FREEDOM_AKI",
      "m_bWaitClick": true,
      "m_fWaitTime": 0,
      "m_Face": "UNIT_SURPRISE",
      "m_CharStrID": "AKI_FREEDOM_NULL_NULL",
      "m_Pos": "C",
      "m_Talk_KOREA": "ÂťZt?",
      "m_fTalkTime": 0.03,
      "m_Talk_USA": "ÂťZt?",
      "m_Talk_JAPAN": "ÂťZt?"
    },
    {
      "m_CutScenID": 10500001,
      "m_CutScenStrID": "LIFETIME_START_NKM_UNIT_C_FREEDOM_AKI",
      "m_bWaitClick": true,
      "m_fWaitTime": 0,
      "m_Face": "UNIT_IDLE",
      "m_CharStrID": "AKI_FREEDOM_NULL_NULL",
      "m_Pos": "C",
      "m_Talk_KOREA": "Âž\f9Z, Âś\u000183\u000184Âś\u000f8`, Âťw\r8Âž\f9ZÂžl\f8! Âť\u000b9\u000185Âži~Âź\r8^ Âś\u000183\u000184Âťp]Âžsp!",
      "m_fTalkTime": 0.03,
      "m_Talk_USA": "Âž\f9Z, Âś\u000183\u000184Âś\u000f8`, Âťw\r8Âž\f9ZÂžl\f8! Âť\u000b9\u000185Âži~Âź\r8^ Âś\u000183\u000184Âťp]Âžsp!",
      "m_Talk_JAPAN": "Âž\f9Z, Âś\u000183\u000184Âś\u000f8`, Âťw\r8Âž\f9ZÂžl\f8! Âť\u000b9\u000185Âži~Âź\r8^ Âś\u000183\u000184Âťp]Âžsp!"
    },
    {
      "m_CutScenID": 10500001,
      "m_CutScenStrID": "LIFETIME_START_NKM_UNIT_C_FREEDOM_AKI",
      "m_bWaitClick": true,
      "m_fWaitTime": 0,
      "m_CharStrID": "AKI_FREEDOM_NULL_NULL",
      "m_Pos": "C",
      "m_Talk_KOREA": "Âś\u000180\n8ÂťvzÂť\u000182\n8 Âź\f9jÂťXj Âž\f8\u000e8ÂťcZ Âť\u000182ZÂťx[ Âť}\u000184Âź`[ÂžoZ Âť`\n8Âś~\n8Âťqn Âžw\n9Âžmd Âžp\f9Âť\u000f9\u000180 Âź\f9nÂťed Âť\u000f8^Âžo\n8 Âť\u000185\u000188Âťc`Âťp\u000184ÂžoZ Âś~Âťo\u000188Âś\u000f9pÂžl\f8!",
      "m_fTalkTime": 0.03,
      "m_Talk_USA": "Âś\u000180\n8ÂťvzÂť\u000182\n8 Âź\f9jÂťXj Âž\f8\u000e8ÂťcZ Âť\u000182ZÂťx[ Âť}\u000184Âź`[ÂžoZ Âť`\n8Âś~\n8Âťqn Âžw\n9Âžmd Âžp\f9Âť\u000f9\u000180 Âź\f9nÂťed Âť\u000f8^Âžo\n8 Âť\u000185\u000188Âťc`Âťp\u000184ÂžoZ Âś~Âťo\u000188Âś\u000f9pÂžl\f8!",
      "m_Talk_JAPAN": "Âś\u000180\n8ÂťvzÂť\u000182\n8 Âź\f9jÂťXj Âž\f8\u000e8ÂťcZ Âť\u000182ZÂťx[ Âť}\u000184Âź`[ÂžoZ Âť`\n8Âś~\n8Âťqn Âžw\n9Âžmd Âžp\f9Âť\u000f9\u000180 Âź\f9nÂťed Âť\u000f8^Âžo\n8 Âť\u000185\u000188Âťc`Âťp\u000184ÂžoZ Âś~Âťo\u000188Âś\u000f9pÂžl\f8!"
    },
    {
      "m_CutScenID": 10500001,
      "m_CutScenStrID": "LIFETIME_START_NKM_UNIT_C_FREEDOM_AKI",
      "m_bWaitClick": false,
      "m_fWaitTime": 0,
      "m_CharStrID": "AKI_FREEDOM_NULL_NULL",
      "m_Pos": "C_D"
    },
    {
      "m_CutScenID": 10500001,
      "m_CutScenStrID": "LIFETIME_START_NKM_UNIT_C_FREEDOM_AKI",
      "m_bWaitClick": true,
      "m_fWaitTime": 0,
      "m_CharStrID": "USER_ADMIN_NULL_NULL",
      "m_Talk_KOREA": "Âž\r8d, Âť^^Âś~dÂž\f9Z ÂžtZ Âź[`Âť\u000b9^ Âžr[Âž\u000b9pÂś\u000f9ZÂž\f9\u000189ÂžoZ Âťw\u000186ÂťcZÂťqo Âź\f9jÂžw\n8.",
      "m_fTalkTime": 0.03,
      "m_Talk_USA": "Âž\r8d, Âť^^Âś~dÂž\f9Z ÂžtZ Âź[`Âť\u000b9^ Âžr[Âž\u000b9pÂś\u000f9ZÂž\f9\u000189ÂžoZ Âťw\u000186ÂťcZÂťqo Âź\f9jÂžw\n8.",
      "m_Talk_JAPAN": "Âž\r8d, Âť^^Âś~dÂž\f9Z ÂžtZ Âź[`Âť\u000b9^ Âžr[Âž\u000b9pÂś\u000f9ZÂž\f9\u000189ÂžoZ Âťw\u000186ÂťcZÂťqo Âź\f9jÂžw\n8."
    },
    {
      "m_CutScenID": 10500001,
      "m_CutScenStrID": "LIFETIME_START_NKM_UNIT_C_FREEDOM_AKI",
      "m_bWaitClick": true,
      "m_fWaitTime": 0,
      "m_Face": "UNIT_HATE",
      "m_CharStrID": "AKI_FREEDOM_NULL_NULL",
      "m_Pos": "C",
      "m_Crash": 40,
      "m_Talk_KOREA": "Âž\f9ZÂž\f9i?! Âťjd Âś~ÂžwgÂťwdÂžo\u000180Âž\f9\u000188!",
      "m_fTalkTime": 0.03,
      "m_Talk_USA": "Âž\f9ZÂž\f9i?! Âťjd Âś~ÂžwgÂťwdÂžo\u000180Âž\f9\u000188!",
      "m_Talk_JAPAN": "Âž\f9ZÂž\f9i?! Âťjd Âś~ÂžwgÂťwdÂžo\u000180Âž\f9\u000188!"
    },
    {
      "m_CutScenID": 10500001,
      "m_CutScenStrID": "LIFETIME_START_NKM_UNIT_C_FREEDOM_AKI",
      "m_bWaitClick": true,
      "m_fWaitTime": 0,
      "m_Face": "UNIT_HATE",
      "m_CharStrID": "AKI_FREEDOM_NULL_NULL",
      "m_Pos": "C",
      "m_Crash": 20,
      "m_Talk_KOREA": "ÂžXzÂž\r8uÂť\u000b9jÂžo\n8 Âžp^ Âť\\\n8Âťpt Âť\u000e8\u000185Âť\u000b8\f8 Âś\u000f8` Âś\u000183\u000184Âťp]Âś\u000f8` Âž\r8zÂť~`Âžn\u000188ÂžZ\u000184Âžl\f8?!",
      "m_fTalkTime": 0.03,
      "m_Talk_USA": "ÂžXzÂž\r8uÂť\u000b9jÂžo\n8 Âžp^ Âť\\\n8Âťpt Âť\u000e8\u000185Âť\u000b8\f8 Âś\u000f8` Âś\u000183\u000184Âťp]Âś\u000f8` Âž\r8zÂť~`Âžn\u000188ÂžZ\u000184Âžl\f8?!",
      "m_Talk_JAPAN": "ÂžXzÂž\r8uÂť\u000b9jÂžo\n8 Âžp^ Âť\\\n8Âťpt Âť\u000e8\u000185Âť\u000b8\f8 Âś\u000f8` Âś\u000183\u000184Âťp]Âś\u000f8` Âž\r8zÂť~`Âžn\u000188ÂžZ\u000184Âžl\f8?!"
    },
    {
      "m_CutScenID": 10500001,
      "m_CutScenStrID": "LIFETIME_START_NKM_UNIT_C_FREEDOM_AKI",
      "m_bWaitClick": false,
      "m_fWaitTime": 0,
      "m_CharStrID": "AKI_FREEDOM_NULL_NULL",
      "m_Pos": "C_D"
    },
    {
      "m_CutScenID": 10500001,
      "m_CutScenStrID": "LIFETIME_START_NKM_UNIT_C_FREEDOM_AKI",
      "m_bWaitClick": true,
      "m_fWaitTime": 0,
      "m_CharStrID": "USER_ADMIN_NULL_NULL",
      "m_Talk_KOREA": "Âś\u000183\u000184Âťvz Âž\r8zÂť}\u000184Âť\u000b8\f8 Âži\\ÂťZtÂťw`......",
      "m_fTalkTime": 0.03,
      "m_Talk_USA": "Âś\u000183\u000184Âťvz Âž\r8zÂť}\u000184Âť\u000b8\f8 Âži\\ÂťZtÂťw`......",
      "m_Talk_JAPAN": "Âś\u000183\u000184Âťvz Âž\r8zÂť}\u000184Âť\u000b8\f8 Âži\\ÂťZtÂťw`......"
    },
    {
      "m_CutScenID": 10500001,
      "m_CutScenStrID": "LIFETIME_START_NKM_UNIT_C_FREEDOM_AKI",
      "m_bWaitClick": true,
      "m_fWaitTime": 0,
      "m_CharStrID": "USER_ADMIN_NULL_NULL",
      "m_Talk_KOREA": "Âžs\u000188Âť\u000b8\f8 Âžm\f8Âś\u000184_ Âž\f9ZÂś\u000185oÂžw\n8 Âž\f9\u000b8ÂžoZ Âťw`Âź\n9\u000188 Âť\\\n8Âťpt Âť\u000e8\u000185Âžh\u000180Âž\f9\u000188Âžw\n8 Âžh\u000180Âž\u000e9`Âś\u000f8pÂťXj.",
      "m_fTalkTime": 0.03,
      "m_Talk_USA": "Âžs\u000188Âť\u000b8\f8 Âžm\f8Âś\u000184_ Âž\f9ZÂś\u000185oÂžw\n8 Âž\f9\u000b8ÂžoZ Âťw`Âź\n9\u000188 Âť\\\n8Âťpt Âť\u000e8\u000185Âžh\u000180Âž\f9\u000188Âžw\n8 Âžh\u000180Âž\u000e9`Âś\u000f8pÂťXj.",
      "m_Talk_JAPAN": "Âžs\u000188Âť\u000b8\f8 Âžm\f8Âś\u000184_ Âž\f9ZÂś\u000185oÂžw\n8 Âž\f9\u000b8ÂžoZ Âťw`Âź\n9\u000188 Âť\\\n8Âťpt Âť\u000e8\u000185Âžh\u000180Âž\f9\u000188Âžw\n8 Âžh\u000180Âž\u000e9`Âś\u000f8pÂťXj."
    },
    {
      "m_CutScenID": 10500001,
      "m_CutScenStrID": "LIFETIME_START_NKM_UNIT_C_FREEDOM_AKI",
      "m_bWaitClick": true,
      "m_fWaitTime": 0,
      "m_CharStrID": "AKI_FREEDOM_NULL_NULL",
      "m_Pos": "C",
      "m_Crash": 40,
      "m_Talk_KOREA": "ÂťwdÂž\f8\n8Âžo\u000180 ÂťZ^Âťz\u000180Âź\f9jÂž\u000b9nÂťZtÂžl\f8, ÂžvoÂťwd!?",
      "m_fTalkTime": 0.03,
      "m_Talk_USA": "ÂťwdÂž\f8\n8Âžo\u000180 ÂťZ^Âťz\u000180Âź\f9jÂž\u000b9nÂťZtÂžl\f8, ÂžvoÂťwd!?",
      "m_Talk_JAPAN": "ÂťwdÂž\f8\n8Âžo\u000180 ÂťZ^Âťz\u000180Âź\f9jÂž\u000b9nÂťZtÂžl\f8, ÂžvoÂťwd!?"
    },
    {
      "m_CutScenID": 10500001,
      "m_CutScenStrID": "LIFETIME_START_NKM_UNIT_C_FREEDOM_AKI",
      "m_bWaitClick": false,
      "m_fWaitTime": 0,
      "m_CharStrID": "AKI_FREEDOM_NULL_NULL",
      "m_Pos": "C_D"
    },
    {
      "m_CutScenID": 10500001,
      "m_CutScenStrID": "LIFETIME_START_NKM_UNIT_C_FREEDOM_AKI",
      "m_bWaitClick": true,
      "m_fWaitTime": 0,
      "m_CharStrID": "USER_ADMIN_NULL_NULL",
      "m_Talk_KOREA": "ÂźodÂžo`. Âś\u000183\u000184 Âť~jÂžoeÂžoZ Âť\u000f9\u000180Âť\u000b9^ ÂťX\u000180Âś~\n8 ÂťZ^Âťz\u000180 ÂžZsÂť\u000182\n8Âťu\u000180Âś\u000f8` ÂžpnÂž\f9^Âź\f9n Âś\u000f8Y Âś~kÂś\u000181~.",
      "m_fTalkTime": 0.03,
      "m_Talk_USA": "ÂźodÂžo`. Âś\u000183\u000184 Âť~jÂžoeÂžoZ Âť\u000f9\u000180Âť\u000b9^ ÂťX\u000180Âś~\n8 ÂťZ^Âťz\u000180 ÂžZsÂť\u000182\n8Âťu\u000180Âś\u000f8` ÂžpnÂž\f9^Âź\f9n Âś\u000f8Y Âś~kÂś\u000181~.",
      "m_Talk_JAPAN": "ÂźodÂžo`. Âś\u000183\u000184 Âť~jÂžoeÂžoZ Âť\u000f9\u000180Âť\u000b9^ ÂťX\u000180Âś~\n8 ÂťZ^Âťz\u000180 ÂžZsÂť\u000182\n8Âťu\u000180Âś\u000f8` ÂžpnÂž\f9^Âź\f9n Âś\u000f8Y Âś~kÂś\u000181~."
    },
    {
      "m_CutScenID": 10500001,
      "m_CutScenStrID": "LIFETIME_START_NKM_UNIT_C_FREEDOM_AKI",
      "m_bWaitClick": true,
      "m_fWaitTime": 0,
      "m_Face": "UNIT_PRIDE",
      "m_CharStrID": "AKI_FREEDOM_NULL_NULL",
      "m_Pos": "C",
      "m_Talk_KOREA": "Âť\u000b9\u000185Âži~Âź\f9jÂžsp. Âžr[Âž\u000b9pÂś\u000f9ZÂž\f9\u000189Âžo\u000180Âť\u000e9\u000180 Âžw\n8Âś\u000184^Âś\u000185`Âžw\n8Âť\u000f9\u000180Âť\u000b9t Âťa\f8 ÂźjZÂž\r8uÂžid ÂťwbÂžo\u000180 ÂťXjÂś~\n8Âž\f9\u000188 Âź\f9jÂž\r8hÂž\f9ZÂžl\f8?",
      "m_fTalkTime": 0.03,
      "m_Talk_USA": "Âť\u000b9\u000185Âži~Âź\f9jÂžsp. Âžr[Âž\u000b9pÂś\u000f9ZÂž\f9\u000189Âžo\u000180Âť\u000e9\u000180 Âžw\n8Âś\u000184^Âś\u000185`Âžw\n8Âť\u000f9\u000180Âť\u000b9t Âťa\f8 ÂźjZÂž\r8uÂžid ÂťwbÂžo\u000180 ÂťXjÂś~\n8Âž\f9\u000188 Âź\f9jÂž\r8hÂž\f9ZÂžl\f8?",
      "m_Talk_JAPAN": "Âť\u000b9\u000185Âži~Âź\f9jÂžsp. Âžr[Âž\u000b9pÂś\u000f9ZÂž\f9\u000189Âžo\u000180Âť\u000e9\u000180 Âžw\n8Âś\u000184^Âś\u000185`Âžw\n8Âť\u000f9\u000180Âť\u000b9t Âťa\f8 ÂźjZÂž\r8uÂžid ÂťwbÂžo\u000180 ÂťXjÂś~\n8Âž\f9\u000188 Âź\f9jÂž\r8hÂž\f9ZÂžl\f8?"
    },
    {
      "m_CutScenID": 10500001,
      "m_CutScenStrID": "LIFETIME_START_NKM_UNIT_C_FREEDOM_AKI",
      "m_bWaitClick": true,
      "m_fWaitTime": 0,
      "m_CharStrID": "AKI_FREEDOM_NULL_NULL",
      "m_Pos": "C",
      "m_Talk_KOREA": "Âžpn Âž\u000b9pÂť[dÂś\u000f9\u000188Âť\u000b8\f8 2Âś\u000180eÂť[Z Âžp\f9ÂťcZ ÂťckÂťh\u000e8Âžh\u000180Âžp\u000184 Âž\r8^Âž\u000b8\u000181Âť\u000b9^Âť\u000b9t. ÂźmiÂźmiÂźmi.",
      "m_fTalkTime": 0.03,
      "m_Talk_USA": "Âžpn Âž\u000b9pÂť[dÂś\u000f9\u000188Âť\u000b8\f8 2Âś\u000180eÂť[Z Âžp\f9ÂťcZ ÂťckÂťh\u000e8Âžh\u000180Âžp\u000184 Âž\r8^Âž\u000b8\u000181Âť\u000b9^Âť\u000b9t. ÂźmiÂźmiÂźmi.",
      "m_Talk_JAPAN": "Âžpn Âž\u000b9pÂť[dÂś\u000f9\u000188Âť\u000b8\f8 2Âś\u000180eÂť[Z Âžp\f9ÂťcZ ÂťckÂťh\u000e8Âžh\u000180Âžp\u000184 Âž\r8^Âž\u000b8\u000181Âť\u000b9^Âť\u000b9t. ÂźmiÂźmiÂźmi."
    },
    {
      "m_CutScenID": 10500001,
      "m_CutScenStrID": "LIFETIME_START_NKM_UNIT_C_FREEDOM_AKI",
      "m_bWaitClick": false,
      "m_fWaitTime": 0,
      "m_CharStrID": "AKI_FREEDOM_NULL_NULL",
      "m_Pos": "C_D"
    },
    {
      "m_CutScenID": 10500001,
      "m_CutScenStrID": "LIFETIME_START_NKM_UNIT_C_FREEDOM_AKI",
      "m_bWaitClick": true,
      "m_fWaitTime": 0,
      "m_CharStrID": "USER_ADMIN_NULL_NULL",
      "m_Talk_KOREA": "Âžo\u000180Âť\u000f8^ Âžo\u000188ÂžoZ Âś\u000f9ZÂś\u000184~Âťqn Âť\u000182ZÂť~nÂź\f9\u000180 Âžs\u000188Âť\u000e9\u000180 ÂťX\u000180 Âť\u000185ZÂž\r8uÂžoj Âž~\u000189Âži[ Âť[\u000184Âź\f9jÂžl~Âťo\u000188ÂťcZ Âž\f9`Âťpt Âžs\u000188ÂťptÂś\u000f9p Âźh^Âť\u000b8\f8Âťa~......",
      "m_fTalkTime": 0.03,
      "m_Talk_USA": "Âžo\u000180Âť\u000f8^ Âžo\u000188ÂžoZ Âś\u000f9ZÂś\u000184~Âťqn Âť\u000182ZÂť~nÂź\f9\u000180 Âžs\u000188Âť\u000e9\u000180 ÂťX\u000180 Âť\u000185ZÂž\r8uÂžoj Âž~\u000189Âži[ Âť[\u000184Âź\f9jÂžl~Âťo\u000188ÂťcZ Âž\f9`Âťpt Âžs\u000188ÂťptÂś\u000f9p Âźh^Âť\u000b8\f8Âťa~......",
      "m_Talk_JAPAN": "Âžo\u000180Âť\u000f8^ Âžo\u000188ÂžoZ Âś\u000f9ZÂś\u000184~Âťqn Âť\u000182ZÂť~nÂź\f9\u000180 Âžs\u000188Âť\u000e9\u000180 ÂťX\u000180 Âť\u000185ZÂž\r8uÂžoj Âž~\u000189Âži[ Âť[\u000184Âź\f9jÂžl~Âťo\u000188ÂťcZ Âž\f9`Âťpt Âžs\u000188ÂťptÂś\u000f9p Âźh^Âť\u000b8\f8Âťa~......"
    },
    {
      "m_CutScenID": 10500001,
      "m_CutScenStrID": "LIFETIME_START_NKM_UNIT_C_FREEDOM_AKI",
      "m_bWaitClick": true,
      "m_fWaitTime": 0,
      "m_CharStrID": "USER_ADMIN_NULL_NULL",
      "m_Talk_KOREA": "Âž\u000b9yÂť\u000b9tÂť\u000e9\u000180 Âžh\u000180Âž\u000e9\f8 Âž^j Âži\\Âžw\n8.",
      "m_fTalkTime": 0.03,
      "m_Talk_USA": "Âž\u000b9yÂť\u000b9tÂť\u000e9\u000180 Âžh\u000180Âž\u000e9\f8 Âž^j Âži\\Âžw\n8.",
      "m_Talk_JAPAN": "Âž\u000b9yÂť\u000b9tÂť\u000e9\u000180 Âžh\u000180Âž\u000e9\f8 Âž^j Âži\\Âžw\n8."
    },
    {
      "m_CutScenID": 10500001,
      "m_CutScenStrID": "LIFETIME_START_NKM_UNIT_C_FREEDOM_AKI",
      "m_bWaitClick": true,
      "m_fWaitTime": 0,
      "m_Face": "UNIT_SERIOUS",
      "m_CharStrID": "AKI_FREEDOM_NULL_NULL",
      "m_Pos": "C",
      "m_Talk_KOREA": "ÂžpZ Âžo\u000184ÂťujÂžk\n8 Âźl`ÂžXzÂťu\u000188 ÂžnZÂź\f9\u000180 Âžo\u000180 Âź\f9nÂťx\u000184 ÂźozÂžYoÂź\f9p Âžt\n8Âť\u000185ZÂś~\n8 ÂťdjÂžh\u000180 Âž\r8^Âž\u000b8\u000181Âť\u000b9^Âť\u000b9t!",
      "m_fTalkTime": 0.03,
      "m_Talk_USA": "ÂžpZ Âžo\u000184ÂťujÂžk\n8 Âźl`ÂžXzÂťu\u000188 ÂžnZÂź\f9\u000180 Âžo\u000180 Âź\f9nÂťx\u000184 ÂźozÂžYoÂź\f9p Âžt\n8Âť\u000185ZÂś~\n8 ÂťdjÂžh\u000180 Âž\r8^Âž\u000b8\u000181Âť\u000b9^Âť\u000b9t!",
      "m_Talk_JAPAN": "ÂžpZ Âžo\u000184ÂťujÂžk\n8 Âźl`ÂžXzÂťu\u000188 ÂžnZÂź\f9\u000180 Âžo\u000180 Âź\f9nÂťx\u000184 ÂźozÂžYoÂź\f9p Âžt\n8Âť\u000185ZÂś~\n8 ÂťdjÂžh\u000180 Âž\r8^Âž\u000b8\u000181Âť\u000b9^Âť\u000b9t!"
    },
    {
      "m_CutScenID": 10500001,
      "m_CutScenStrID": "LIFETIME_START_NKM_UNIT_C_FREEDOM_AKI",
      "m_bWaitClick": false,
      "m_fWaitTime": 0,
      "m_CharStrID": "AKI_FREEDOM_NULL_NULL",
      "m_Pos": "C_D"
    },
    {
      "m_CutScenID": 10500001,
      "m_CutScenStrID": "LIFETIME_START_NKM_UNIT_C_FREEDOM_AKI",
      "m_bWaitClick": true,
      "m_fWaitTime": 0,
      "m_CharStrID": "USER_ADMIN_NULL_NULL",
      "m_Talk_KOREA": "Âź\f9jÂź\f9j, Âś\u000183\u000184Âťp]Âť\u000b9tÂť\u000e9\u000180 Âť\u000b9tÂźh_Âžo\u000180Âś\u000181~. Âž\r8dÂťZtÂť\u000b8\f8 ÂžXzÂť\r8`Âžo\u000180 Âž\\\f8Âžw\n9Âź\f9\u000180ÂžZn Âžr\u000b9Âž\f9Z.",
      "m_fTalkTime": 0.03,
      "m_Talk_USA": "Âź\f9jÂź\f9j, Âś\u000183\u000184Âťp]Âť\u000b9tÂť\u000e9\u000180 Âť\u000b9tÂźh_Âžo\u000180Âś\u000181~. Âž\r8dÂťZtÂť\u000b8\f8 ÂžXzÂť\r8`Âžo\u000180 Âž\\\f8Âžw\n9Âź\f9\u000180ÂžZn Âžr\u000b9Âž\f9Z.",
      "m_Talk_JAPAN": "Âź\f9jÂź\f9j, Âś\u000183\u000184Âťp]Âť\u000b9tÂť\u000e9\u000180 Âť\u000b9tÂźh_Âžo\u000180Âś\u000181~. Âž\r8dÂťZtÂť\u000b8\f8 ÂžXzÂť\r8`Âžo\u000180 Âž\\\f8Âžw\n9Âź\f9\u000180ÂžZn Âžr\u000b9Âž\f9Z."
    },
    {
      "m_CutScenID": 10500001,
      "m_CutScenStrID": "LIFETIME_START_NKM_UNIT_C_FREEDOM_AKI",
      "m_bWaitClick": true,
      "m_fWaitTime": 0,
      "m_Face": "UNIT_HATE",
      "m_CharStrID": "AKI_FREEDOM_NULL_NULL",
      "m_Pos": "C",
      "m_Crash": 20,
      "m_Talk_KOREA": "Âžl~Âžn\u000188...... Âž\u000185jÂžXzÂź\f9\u000180......",
      "m_fTalkTime": 0.03,
      "m_Talk_USA": "Âžl~Âžn\u000188...... Âž\u000185jÂžXzÂź\f9\u000180......",
      "m_Talk_JAPAN": "Âžl~Âžn\u000188...... Âž\u000185jÂžXzÂź\f9\u000180......"
    },
    {
      "m_CutScenID": 10500001,
      "m_CutScenStrID": "LIFETIME_START_NKM_UNIT_C_FREEDOM_AKI",
      "m_bWaitClick": true,
      "m_fWaitTime": 0,
      "m_Face": "UNIT_DESPAIR",
      "m_CharStrID": "AKI_FREEDOM_NULL_NULL",
      "m_Pos": "C",
      "m_Crash": 10,
      "m_Talk_KOREA": "Âś\u000183\u000184Âž\u000185jÂťw` Âž\f9\r8Âžn\u000188Âťqn Âźc_ÂžYo Âžo\u000188Âź\f9jÂžw\n8 Âž\f9\u000b8Âś\u000f9p ÂźYÂž\r8dÂźYÂž\r8d Âť\\\n8 Âž^jÂťw` Âž\r8^Âť\u000b9tÂť\u000e9\u000180......",
      "m_fTalkTime": 0.03,
      "m_Talk_USA": "Âś\u000183\u000184Âž\u000185jÂťw` Âž\f9\r8Âžn\u000188Âťqn Âźc_ÂžYo Âžo\u000188Âź\f9jÂžw\n8 Âž\f9\u000b8Âś\u000f9p ÂźYÂž\r8dÂźYÂž\r8d Âť\\\n8 Âž^jÂťw` Âž\r8^Âť\u000b9tÂť\u000e9\u000180......",
      "m_Talk_JAPAN": "Âś\u000183\u000184Âž\u000185jÂťw` Âž\f9\r8Âžn\u000188Âťqn Âźc_ÂžYo Âžo\u000188Âź\f9jÂžw\n8 Âž\f9\u000b8Âś\u000f9p ÂźYÂž\r8dÂźYÂž\r8d Âť\\\n8 Âž^jÂťw` Âž\r8^Âť\u000b9tÂť\u000e9\u000180......"
    },
    {
      "m_CutScenID": 10500001,
      "m_CutScenStrID": "LIFETIME_START_NKM_UNIT_C_FREEDOM_AKI",
      "m_bWaitClick": true,
      "m_fWaitTime": 0,
      "m_Face": "UNIT_LAUGH",
      "m_CharStrID": "AKI_FREEDOM_NULL_NULL",
      "m_Pos": "C",
      "m_Crash": 40,
      "m_Talk_KOREA": "Âžoe! Âžo\u000180 Âžp\f9ÂťcZÂž\f9\u000188 Âžh\u000188Âťw^ÂťgpÂžw\n8!",
      "m_fTalkTime": 0.03,
      "m_Talk_USA": "Âžoe! Âžo\u000180 Âžp\f9ÂťcZÂž\f9\u000188 Âžh\u000188Âťw^ÂťgpÂžw\n8!",
      "m_Talk_JAPAN": "Âžoe! Âžo\u000180 Âžp\f9ÂťcZÂž\f9\u000188 Âžh\u000188Âťw^ÂťgpÂžw\n8!"
    }
  ],
  "unsupportedCount": 0,
  "unsupported": []
}