{
  "source": "<project-root>\\gameplay-tables-decompiled\\StreamingAssets\\ab_script\\luac\\LUA_POST_TEMPLET.lua",
  "rootName": "POST_TEMPLET",
  "recordCount": 12,
  "records": [
    {
      "m_PostID": 0,
      "m_PostType": "NORMAL",
      "m_AllowReceiveAll": true
    },
    {
      "m_PostID": 1,
      "m_PostType": "ANNOUNCEMENT",
      "m_AllowReceiveAll": true
    },
    {
      "m_PostID": 2,
      "m_PostType": "SYSTEM",
      "m_AllowReceiveAll": true
    },
    {
      "m_PostID": 3,
      "m_PostType": "GM",
      "m_AllowReceiveAll": true
    },
    {
      "m_PostID": 4,
      "m_PostType": "REWARD_EVENT",
      "m_AllowReceiveAll": true
    },
    {
      "m_PostID": 5,
      "m_PostType": "SHOP_PURCHASE",
      "m_AllowReceiveAll": true
    },
    {
      "m_PostID": 6,
      "m_PostType": "WEB_COUPON",
      "m_AllowReceiveAll": true
    },
    {
      "m_PostID": 7,
      "m_PostType": "OFFERWAL",
      "m_AllowReceiveAll": true
    },
    {
      "m_PostID": 8,
      "m_PostType": "ON_TIME_EVENT",
      "m_AllowReceiveAll": true
    },
    {
      "m_PostID": 9,
      "m_PostType": "BSIDE_COUPON",
      "m_AllowReceiveAll": true
    },
    {
      "m_PostID": 100,
      "m_PostType": "NORMAL",
      "m_PostPeriod": 30,
      "m_AllowReceiveAll": false
    },
    {
      "m_PostID": 101,
      "m_PostType": "NORMAL",
      "m_PostPeriod": 7,
      "m_AllowReceiveAll": false
    }
  ],
  "root": [
    {
      "m_PostID": 0,
      "m_PostType": "NORMAL",
      "m_AllowReceiveAll": true
    },
    {
      "m_PostID": 1,
      "m_PostType": "ANNOUNCEMENT",
      "m_AllowReceiveAll": true
    },
    {
      "m_PostID": 2,
      "m_PostType": "SYSTEM",
      "m_AllowReceiveAll": true
    },
    {
      "m_PostID": 3,
      "m_PostType": "GM",
      "m_AllowReceiveAll": true
    },
    {
      "m_PostID": 4,
      "m_PostType": "REWARD_EVENT",
      "m_AllowReceiveAll": true
    },
    {
      "m_PostID": 5,
      "m_PostType": "SHOP_PURCHASE",
      "m_AllowReceiveAll": true
    },
    {
      "m_PostID": 6,
      "m_PostType": "WEB_COUPON",
      "m_AllowReceiveAll": true
    },
    {
      "m_PostID": 7,
      "m_PostType": "OFFERWAL",
      "m_AllowReceiveAll": true
    },
    {
      "m_PostID": 8,
      "m_PostType": "ON_TIME_EVENT",
      "m_AllowReceiveAll": true
    },
    {
      "m_PostID": 9,
      "m_PostType": "BSIDE_COUPON",
      "m_AllowReceiveAll": true
    },
    {
      "m_PostID": 100,
      "m_PostType": "NORMAL",
      "m_PostPeriod": 30,
      "m_AllowReceiveAll": false
    },
    {
      "m_PostID": 101,
      "m_PostType": "NORMAL",
      "m_PostPeriod": 7,
      "m_AllowReceiveAll": false
    }
  ],
  "unsupportedCount": 0,
  "unsupported": []
}